Workbook

Sheet 2023 Forecast Totals
A1: Type of Annuals per Month | P1: Totals
A2: Total hired billable technicans | D2: 26 | E2: 26 | F2: 26 | G2: 26 | H2: 26 | I2: 26 | J2: 26 | K2: 26 | L2: 26 | M2: 26 | N2: 26 | O2: 26 | P2: =AVERAGE(D2:O2) -> 26 | Q2: 30 | R2: 36 | S2: 36 | T2: 36 | U2: 36 | V2: 36 | W2: 36 | X2: 30 | Y2: 30 | Z2: 30 | AA2: 30 | AB2: 30 | AC2: =AVERAGE(Q2:AB2) -> 33 | AD2: 30 | AE2: 30 | AF2: 30 | AG2: 30 | AH2: 30 | AI2: 30 | AJ2: 30 | AK2: 30 | AL2: 30 | AM2: 30 | AN2: 30 | AO2: 30 | AP2: =AVERAGE(AD2:AO2) -> 30
A3: Months | D3: Jan | E3: Feb | F3: Mar | G3: Apr | H3: May | I3: Jun | J3: Jul | K3: Aug | L3: Sep | M3: Oct | N3: Nov | O3: Dec | P3: 2024 Totals | Q3: Jan | R3: Feb | S3: Mar | T3: Apr | U3: May | V3: Jun | W3: Jul | X3: Aug | Y3: Sep | Z3: Oct | AA3: Nov | AB3: Dec | AC3: 2025 Totals | AD3: Jan | AE3: Feb | AF3: Mar | AG3: Apr | AH3: May | AI3: Jun | AJ3: Jul | AK3: Aug | AL3: Sep | AM3: Oct | AN3: Nov | AO3: Dec | AP3: 2026 Totals
A4: JSX Heavy Inspection | D4: 1 | E4: 1 | F4: 1 | G4: 1 | H4: 1 | I4: 1 | J4: 1 | K4: 1 | L4: 1 | M4: 1 | N4: 1 | O4: 1 | P4: =SUM(D4:O4) -> 12 | Q4: 1 | R4: 1 | S4: 1 | T4: 1 | U4: 1 | W4: 1 | X4: 1 | Y4: 1 | Z4: 1 | AA4: 1 | AC4: =SUM(Q4:AB4) -> 10 | AD4: 1 | AE4: 1 | AF4: 1 | AG4: 1 | AH4: 1 | AI4: 1 | AJ4: 1 | AK4: 1 | AL4: 1 | AM4: 1 | AN4: 1 | AO4: 1 | AP4: =SUM(AD4:AO4) -> 12
A5: JSX Line Check | D5: 24 | E5: 36 | F5: 48 | G5: 60 | H5: 60 | I5: 60 | J5: 72 | K5: 72 | L5: 84 | M5: 84 | N5: 84 | O5: 84 | P5: =SUM(D5:O5) -> 768 | Q5: 84 | R5: 84 | S5: 84 | T5: 84 | U5: 84 | V5: 84 | W5: 84 | X5: 84 | Y5: 84 | Z5: 84 | AA5: 84 | AB5: 84 | AC5: =SUM(Q5:AB5) -> 1008 | AD5: 84 | AE5: 84 | AF5: 84 | AG5: 84 | AH5: 84 | AI5: 84 | AJ5: 84 | AK5: 84 | AL5: 84 | AM5: 84 | AN5: 84 | AO5: 84 | AP5: =SUM(AD5:AO5) -> 1008
A6: JSX First Flight of the day | D6: 2 | E6: 3 | F6: 4 | G6: 5 | H6: 5 | I6: 5 | J6: 6 | K6: 6 | L6: 7 | M6: 7 | N6: 7 | O6: 7 | P6: =SUM(D6:O6) -> 64 | Q6: 7 | R6: 7 | S6: 7 | T6: 7 | U6: 7 | V6: 7 | W6: 7 | X6: 7 | Y6: 7 | Z6: 7 | AA6: 7 | AB6: 7 | AC6: =SUM(Q6:AB6) -> 84 | AD6: 7 | AE6: 7 | AF6: 7 | AG6: 7 | AH6: 7 | AI6: 7 | AJ6: 7 | AK6: 7 | AL6: 7 | AM6: 7 | AN6: 7 | AO6: 7 | AP6: =SUM(AD6:AO6) -> 84
A7: JSX AOG MX | D7: 2 | E7: 3 | F7: 4 | G7: 5 | H7: 5 | I7: 5 | J7: 6 | K7: 6 | L7: 7 | M7: 7 | N7: 7 | O7: 7 | P7: =SUM(D7:O7) -> 64 | Q7: 7 | R7: 7 | S7: 7 | T7: 7 | U7: 7 | V7: 7 | W7: 7 | X7: 7 | Y7: 7 | Z7: 7 | AA7: 7 | AB7: 7 | AC7: =SUM(Q7:AB7) -> 84 | AD7: 7 | AE7: 7 | AF7: 7 | AG7: 7 | AH7: 7 | AI7: 7 | AJ7: 7 | AK7: 7 | AL7: 7 | AM7: 7 | AN7: 7 | AO7: 7 | AP7: =SUM(AD7:AO7) -> 84
A8: Retail MX | P8: =SUM(D8:O8) -> 0 | AC8: =SUM(Q8:AB8) -> 0 | AP8: =SUM(AD8:AO8) -> 0
A9: Retail AOG | P9: =SUM(D9:O9) -> 0 | AC9: =SUM(Q9:AB9) -> 0 | AP9: =SUM(AD9:AO9) -> 0
A10: Placeholder | P10: =SUM(D10:O10) -> 0 | AC10: =SUM(Q10:AB10) -> 0 | AP10: =SUM(AD10:AO10) -> 0
A11: Placeholder | P11: =SUM(D11:O11) -> 0 | AC11: =SUM(Q11:AB11) -> 0 | AP11: =SUM(AD11:AO11) -> 0
A12: Placeholder | P12: =SUM(D12:O12) -> 0 | AC12: =SUM(Q12:AB12) -> 0 | AP12: =SUM(AD12:AO12) -> 0
A14: Total Aircraft | D14: =SUM(D4:D12) -> 29 | E14: =SUM(E4:E12) -> 43 | F14: =SUM(F4:F12) -> 57 | G14: =SUM(G4:G12) -> 71 | H14: =SUM(H4:H12) -> 71 | I14: =SUM(I4:I12) -> 71 | J14: =SUM(J4:J12) -> 85 | K14: =SUM(K4:K12) -> 85 | ... O14: =SUM(O4:O12) -> 99 | P14: =SUM(D14:O14) -> 908 | Q14: =SUM(Q4:Q12) -> 99 | R14: =SUM(R4:R12) -> 99 | S14: =SUM(S4:S12) -> 99 | T14: =SUM(T4:T12) -> 99 | U14: =SUM(U4:U12) -> 99 | V14: =SUM(V4:V12) -> 98 | W14: =SUM(W4:W12) -> 99 | X14: =SUM(X4:X12) -> 99 | ... AO14: =SUM(AO4:AO12) -> 99 | AP14: =SUM(AD14:AO14) -> 1188
A15: Hangar Capacity | B15: 2
A16: Total hangar bays unused | D16: =$B$15-D14 -> -27 | E16: =$B$15-E14 -> -41 | F16: =$B$15-F14 -> -55 | G16: =$B$15-G14 -> -69 | H16: =$B$15-H14 -> -69 | I16: =$B$15-I14 -> -69 | J16: =$B$15-J14 -> -83 | K16: =$B$15-K14 -> -83 | ... O16: =$B$15-O14 -> -97 | Q16: =$B$15-Q14 -> -97 | R16: =$B$15-R14 -> -97 | S16: =$B$15-S14 -> -97 | T16: =$B$15-T14 -> -97 | U16: =$B$15-U14 -> -97 | V16: =$B$15-V14 -> -96 | W16: =$B$15-W14 -> -97 | X16: =$B$15-X14 -> -97 | ... AB16: =$B$15-AB14 -> -96 | AD16: =$B$15-AD14 -> -97 | AE16: =$B$15-AE14 -> -97 | AF16: =$B$15-AF14 -> -97 | AG16: =$B$15-AG14 -> -97 | AH16: =$B$15-AH14 -> -97 | AI16: =$B$15-AI14 -> -97 | AJ16: =$B$15-AJ14 -> -97 | AK16: =$B$15-AK14 -> -97 | ... AO16: =$B$15-AO14 -> -97
A18: Hours per month
B19: INSP Hours | C19: Repair Hours | D19: Jan | E19: Feb | F19: Mar | G19: Apr | H19: May | I19: Jun | J19: Jul | K19: Aug | L19: Sep | M19: Oct | N19: Nov | O19: Dec | Q19: Jan | R19: Feb | S19: Mar | T19: Apr | U19: May | V19: Jun | W19: Jul | X19: Aug | Y19: Sep | Z19: Oct | AA19: Nov | AB19: Dec | AD19: Jan | AE19: Feb | AF19: Mar | AG19: Apr | AH19: May | AI19: Jun | AJ19: Jul | AK19: Aug | AL19: Sep | AM19: Oct | AN19: Nov | AO19: Dec
A20: JSX Heavy Inspection | B20: 2500 | C20: 500 | D20: =(D4*$B20)+(D4*$C20) -> 3000 | E20: =(E4*$B20)+(E4*$C20) -> 3000 | F20: =(F4*$B20)+(F4*$C20) -> 3000 | G20: =(G4*$B20)+(G4*$C20) -> 3000 | H20: =(H4*$B20)+(H4*$C20) -> 3000 | I20: =(I4*$B20)+(I4*$C20) -> 3000 | J20: =(J4*$B20)+(J4*$C20) -> 3000 | K20: =(K4*$B20)+(K4*$C20) -> 3000 | ... O20: =(O4*$B20)+(O4*$C20) -> 3000 | P20: =SUM(D20:O20) -> 36000 | Q20: =(Q4*$B20)+(Q4*$C20) -> 3000 | R20: =(R4*$B20)+(R4*$C20) -> 3000 | S20: =(S4*$B20)+(S4*$C20) -> 3000 | T20: =(T4*$B20)+(T4*$C20) -> 3000 | U20: =(U4*$B20)+(U4*$C20) -> 3000 | V20: =(V4*$B20)+(V4*$C20) -> 0 | W20: =(W4*$B20)+(W4*$C20) -> 3000 | X20: =(X4*$B20)+(X4*$C20) -> 3000 | ... AB20: =(AB4*$B20)+(AB4*$C20) -> 0 | AC20: =SUM(Q20:AB20) -> 30000 | AD20: =(AD4*$B20)+(AD4*$C20) -> 3000 | AE20: =(AE4*$B20)+(AE4*$C20) -> 3000 | AF20: =(AF4*$B20)+(AF4*$C20) -> 3000 | AG20: =(AG4*$B20)+(AG4*$C20) -> 3000 | AH20: =(AH4*$B20)+(AH4*$C20) -> 3000 | AI20: =(AI4*$B20)+(AI4*$C20) -> 3000 | AJ20: =(AJ4*$B20)+(AJ4*$C20) -> 3000 | AK20: =(AK4*$B20)+(AK4*$C20) -> 3000 | ... AO20: =(AO4*$B20)+(AO4*$C20) -> 3000 | AP20: =SUM(AD20:AO20) -> 36000
A21: JSX Line Check | B21: 2 | D21: =(D5*$B21)+(D5*$C21) -> 48 | E21: =(E5*$B21)+(E5*$C21) -> 72 | F21: =(F5*$B21)+(F5*$C21) -> 96 | G21: =(G5*$B21)+(G5*$C21) -> 120 | H21: =(H5*$B21)+(H5*$C21) -> 120 | I21: =(I5*$B21)+(I5*$C21) -> 120 | J21: =(J5*$B21)+(J5*$C21) -> 144 | K21: =(K5*$B21)+(K5*$C21) -> 144 | ... O21: =(O5*$B21)+(O5*$C21) -> 168 | P21: =SUM(D21:O21) -> 1536 | Q21: =(Q5*$B21)+(Q5*$C21) -> 168 | R21: =(R5*$B21)+(R5*$C21) -> 168 | S21: =(S5*$B21)+(S5*$C21) -> 168 | T21: =(T5*$B21)+(T5*$C21) -> 168 | U21: =(U5*$B21)+(U5*$C21) -> 168 | V21: =(V5*$B21)+(V5*$C21) -> 168 | W21: =(W5*$B21)+(W5*$C21) -> 168 | X21: =(X5*$B21)+(X5*$C21) -> 168 | ... AB21: =(AB5*$B21)+(AB5*$C21) -> 168 | AC21: =SUM(Q21:AB21) -> 2016 | AD21: =(AD5*$B21)+(AD5*$C21) -> 168 | AE21: =(AE5*$B21)+(AE5*$C21) -> 168 | AF21: =(AF5*$B21)+(AF5*$C21) -> 168 | AG21: =(AG5*$B21)+(AG5*$C21) -> 168 | AH21: =(AH5*$B21)+(AH5*$C21) -> 168 | AI21: =(AI5*$B21)+(AI5*$C21) -> 168 | AJ21: =(AJ5*$B21)+(AJ5*$C21) -> 168 | AK21: =(AK5*$B21)+(AK5*$C21) -> 168 | ... AO21: =(AO5*$B21)+(AO5*$C21) -> 168 | AP21: =SUM(AD21:AO21) -> 2016
A22: JSX First Flight of the day | B22: 1.5 | D22: =(D6*$B22)+(D6*$C22) -> 3 | E22: =(E6*$B22)+(E6*$C22) -> 4.5 | F22: =(F6*$B22)+(F6*$C22) -> 6 | G22: =(G6*$B22)+(G6*$C22) -> 7.5 | H22: =(H6*$B22)+(H6*$C22) -> 7.5 | I22: =(I6*$B22)+(I6*$C22) -> 7.5 | J22: =(J6*$B22)+(J6*$C22) -> 9 | K22: =(K6*$B22)+(K6*$C22) -> 9 | ... O22: =(O6*$B22)+(O6*$C22) -> 10.5 | P22: =SUM(D22:O22) -> 96 | Q22: =(Q6*$B22)+(Q6*$C22) -> 10.5 | R22: =(R6*$B22)+(R6*$C22) -> 10.5 | S22: =(S6*$B22)+(S6*$C22) -> 10.5 | T22: =(T6*$B22)+(T6*$C22) -> 10.5 | U22: =(U6*$B22)+(U6*$C22) -> 10.5 | V22: =(V6*$B22)+(V6*$C22) -> 10.5 | W22: =(W6*$B22)+(W6*$C22) -> 10.5 | X22: =(X6*$B22)+(X6*$C22) -> 10.5 | ... AB22: =(AB6*$B22)+(AB6*$C22) -> 10.5 | AC22: =SUM(Q22:AB22) -> 126 | AD22: =(AD6*$B22)+(AD6*$C22) -> 10.5 | AE22: =(AE6*$B22)+(AE6*$C22) -> 10.5 | AF22: =(AF6*$B22)+(AF6*$C22) -> 10.5 | AG22: =(AG6*$B22)+(AG6*$C22) -> 10.5 | AH22: =(AH6*$B22)+(AH6*$C22) -> 10.5 | AI22: =(AI6*$B22)+(AI6*$C22) -> 10.5 | AJ22: =(AJ6*$B22)+(AJ6*$C22) -> 10.5 | AK22: =(AK6*$B22)+(AK6*$C22) -> 10.5 | ... AO22: =(AO6*$B22)+(AO6*$C22) -> 10.5 | AP22: =SUM(AD22:AO22) -> 126
A23: JSX AOG MX | B23: 10 | D23: =(D7*$B23)+(D7*$C23) -> 20 | E23: =(E7*$B23)+(E7*$C23) -> 30 | F23: =(F7*$B23)+(F7*$C23) -> 40 | G23: =(G7*$B23)+(G7*$C23) -> 50 | H23: =(H7*$B23)+(H7*$C23) -> 50 | I23: =(I7*$B23)+(I7*$C23) -> 50 | J23: =(J7*$B23)+(J7*$C23) -> 60 | K23: =(K7*$B23)+(K7*$C23) -> 60 | ... O23: =(O7*$B23)+(O7*$C23) -> 70 | P23: =SUM(D23:O23) -> 640 | Q23: =(Q7*$B23)+(Q7*$C23) -> 70 | R23: =(R7*$B23)+(R7*$C23) -> 70 | S23: =(S7*$B23)+(S7*$C23) -> 70 | T23: =(T7*$B23)+(T7*$C23) -> 70 | U23: =(U7*$B23)+(U7*$C23) -> 70 | V23: =(V7*$B23)+(V7*$C23) -> 70 | W23: =(W7*$B23)+(W7*$C23) -> 70 | X23: =(X7*$B23)+(X7*$C23) -> 70 | ... AB23: =(AB7*$B23)+(AB7*$C23) -> 70 | AC23: =SUM(Q23:AB23) -> 840 | AD23: =(AD7*$B23)+(AD7*$C23) -> 70 | AE23: =(AE7*$B23)+(AE7*$C23) -> 70 | AF23: =(AF7*$B23)+(AF7*$C23) -> 70 | AG23: =(AG7*$B23)+(AG7*$C23) -> 70 | AH23: =(AH7*$B23)+(AH7*$C23) -> 70 | AI23: =(AI7*$B23)+(AI7*$C23) -> 70 | AJ23: =(AJ7*$B23)+(AJ7*$C23) -> 70 | AK23: =(AK7*$B23)+(AK7*$C23) -> 70 | ... AO23: =(AO7*$B23)+(AO7*$C23) -> 70 | AP23: =SUM(AD23:AO23) -> 840
A24: Retail MX | D24: =(D8*$B24)+(D8*$C24) -> 0 | E24: =(E8*$B24)+(E8*$C24) -> 0 | F24: =(F8*$B24)+(F8*$C24) -> 0 | G24: =(G8*$B24)+(G8*$C24) -> 0 | H24: =(H8*$B24)+(H8*$C24) -> 0 | I24: =(I8*$B24)+(I8*$C24) -> 0 | J24: =(J8*$B24)+(J8*$C24) -> 0 | K24: =(K8*$B24)+(K8*$C24) -> 0 | ... O24: =(O8*$B24)+(O8*$C24) -> 0 | P24: =SUM(D24:O24) -> 0 | Q24: =(Q8*$B24)+(Q8*$C24) -> 0 | R24: =(R8*$B24)+(R8*$C24) -> 0 | S24: =(S8*$B24)+(S8*$C24) -> 0 | T24: =(T8*$B24)+(T8*$C24) -> 0 | U24: =(U8*$B24)+(U8*$C24) -> 0 | V24: =(V8*$B24)+(V8*$C24) -> 0 | W24: =(W8*$B24)+(W8*$C24) -> 0 | X24: =(X8*$B24)+(X8*$C24) -> 0 | ... AB24: =(AB8*$B24)+(AB8*$C24) -> 0 | AC24: =SUM(Q24:AB24) -> 0 | AD24: =(AD8*$B24)+(AD8*$C24) -> 0 | AE24: =(AE8*$B24)+(AE8*$C24) -> 0 | AF24: =(AF8*$B24)+(AF8*$C24) -> 0 | AG24: =(AG8*$B24)+(AG8*$C24) -> 0 | AH24: =(AH8*$B24)+(AH8*$C24) -> 0 | AI24: =(AI8*$B24)+(AI8*$C24) -> 0 | AJ24: =(AJ8*$B24)+(AJ8*$C24) -> 0 | AK24: =(AK8*$B24)+(AK8*$C24) -> 0 | ... AO24: =(AO8*$B24)+(AO8*$C24) -> 0 | AP24: =SUM(AD24:AO24) -> 0
A25: Retail AOG | D25: =(D9*$B25)+(D9*$C25) -> 0 | E25: =(E9*$B25)+(E9*$C25) -> 0 | F25: =(F9*$B25)+(F9*$C25) -> 0 | G25: =(G9*$B25)+(G9*$C25) -> 0 | H25: =(H9*$B25)+(H9*$C25) -> 0 | I25: =(I9*$B25)+(I9*$C25) -> 0 | J25: =(J9*$B25)+(J9*$C25) -> 0 | K25: =(K9*$B25)+(K9*$C25) -> 0 | ... O25: =(O9*$B25)+(O9*$C25) -> 0 | P25: =SUM(D25:O25) -> 0 | Q25: =(Q9*$B25)+(Q9*$C25) -> 0 | R25: =(R9*$B25)+(R9*$C25) -> 0 | S25: =(S9*$B25)+(S9*$C25) -> 0 | T25: =(T9*$B25)+(T9*$C25) -> 0 | U25: =(U9*$B25)+(U9*$C25) -> 0 | V25: =(V9*$B25)+(V9*$C25) -> 0 | W25: =(W9*$B25)+(W9*$C25) -> 0 | X25: =(X9*$B25)+(X9*$C25) -> 0 | ... AB25: =(AB9*$B25)+(AB9*$C25) -> 0 | AC25: =SUM(Q25:AB25) -> 0 | AD25: =(AD9*$B25)+(AD9*$C25) -> 0 | AE25: =(AE9*$B25)+(AE9*$C25) -> 0 | AF25: =(AF9*$B25)+(AF9*$C25) -> 0 | AG25: =(AG9*$B25)+(AG9*$C25) -> 0 | AH25: =(AH9*$B25)+(AH9*$C25) -> 0 | AI25: =(AI9*$B25)+(AI9*$C25) -> 0 | AJ25: =(AJ9*$B25)+(AJ9*$C25) -> 0 | AK25: =(AK9*$B25)+(AK9*$C25) -> 0 | ... AO25: =(AO9*$B25)+(AO9*$C25) -> 0 | AP25: =SUM(AD25:AO25) -> 0
A26: Placeholder | D26: =(D10*$B26)+(D10*$C26) -> 0 | E26: =(E10*$B26)+(E10*$C26) -> 0 | F26: =(F10*$B26)+(F10*$C26) -> 0 | G26: =(G10*$B26)+(G10*$C26) -> 0 | H26: =(H10*$B26)+(H10*$C26) -> 0 | I26: =(I10*$B26)+(I10*$C26) -> 0 | J26: =(J10*$B26)+(J10*$C26) -> 0 | K26: =(K10*$B26)+(K10*$C26) -> 0 | ... O26: =(O10*$B26)+(O10*$C26) -> 0 | P26: =SUM(D26:O26) -> 0 | Q26: =(Q10*$B26)+(Q10*$C26) -> 0 | R26: =(R10*$B26)+(R10*$C26) -> 0 | S26: =(S10*$B26)+(S10*$C26) -> 0 | T26: =(T10*$B26)+(T10*$C26) -> 0 | U26: =(U10*$B26)+(U10*$C26) -> 0 | V26: =(V10*$B26)+(V10*$C26) -> 0 | W26: =(W10*$B26)+(W10*$C26) -> 0 | X26: =(X10*$B26)+(X10*$C26) -> 0 | ... AB26: =(AB10*$B26)+(AB10*$C26) -> 0 | AC26: =SUM(Q26:AB26) -> 0 | AD26: =(AD10*$B26)+(AD10*$C26) -> 0 | AE26: =(AE10*$B26)+(AE10*$C26) -> 0 | AF26: =(AF10*$B26)+(AF10*$C26) -> 0 | AG26: =(AG10*$B26)+(AG10*$C26) -> 0 | AH26: =(AH10*$B26)+(AH10*$C26) -> 0 | AI26: =(AI10*$B26)+(AI10*$C26) -> 0 | AJ26: =(AJ10*$B26)+(AJ10*$C26) -> 0 | AK26: =(AK10*$B26)+(AK10*$C26) -> 0 | ... AO26: =(AO10*$B26)+(AO10*$C26) -> 0 | AP26: =SUM(AD26:AO26) -> 0
A27: Placeholder | D27: =(D11*$B27)+(D11*$C27) -> 0 | E27: =(E11*$B27)+(E11*$C27) -> 0 | F27: =(F11*$B27)+(F11*$C27) -> 0 | G27: =(G11*$B27)+(G11*$C27) -> 0 | H27: =(H11*$B27)+(H11*$C27) -> 0 | I27: =(I11*$B27)+(I11*$C27) -> 0 | J27: =(J11*$B27)+(J11*$C27) -> 0 | K27: =(K11*$B27)+(K11*$C27) -> 0 | ... O27: =(O11*$B27)+(O11*$C27) -> 0 | P27: =SUM(D27:O27) -> 0 | Q27: =(Q11*$B27)+(Q11*$C27) -> 0 | R27: =(R11*$B27)+(R11*$C27) -> 0 | S27: =(S11*$B27)+(S11*$C27) -> 0 | T27: =(T11*$B27)+(T11*$C27) -> 0 | U27: =(U11*$B27)+(U11*$C27) -> 0 | V27: =(V11*$B27)+(V11*$C27) -> 0 | W27: =(W11*$B27)+(W11*$C27) -> 0 | X27: =(X11*$B27)+(X11*$C27) -> 0 | ... AB27: =(AB11*$B27)+(AB11*$C27) -> 0 | AC27: =SUM(Q27:AB27) -> 0 | AD27: =(AD11*$B27)+(AD11*$C27) -> 0 | AE27: =(AE11*$B27)+(AE11*$C27) -> 0 | AF27: =(AF11*$B27)+(AF11*$C27) -> 0 | AG27: =(AG11*$B27)+(AG11*$C27) -> 0 | AH27: =(AH11*$B27)+(AH11*$C27) -> 0 | AI27: =(AI11*$B27)+(AI11*$C27) -> 0 | AJ27: =(AJ11*$B27)+(AJ11*$C27) -> 0 | AK27: =(AK11*$B27)+(AK11*$C27) -> 0 | ... AO27: =(AO11*$B27)+(AO11*$C27) -> 0 | AP27: =SUM(AD27:AO27) -> 0
A28: Placeholder | D28: =(D12*$B28)+(D12*$C28) -> 0 | E28: =(E12*$B28)+(E12*$C28) -> 0 | F28: =(F12*$B28)+(F12*$C28) -> 0 | G28: =(G12*$B28)+(G12*$C28) -> 0 | H28: =(H12*$B28)+(H12*$C28) -> 0 | I28: =(I12*$B28)+(I12*$C28) -> 0 | J28: =(J12*$B28)+(J12*$C28) -> 0 | K28: =(K12*$B28)+(K12*$C28) -> 0 | ... O28: =(O12*$B28)+(O12*$C28) -> 0 | P28: =SUM(D28:O28) -> 0 | Q28: =(Q12*$B28)+(Q12*$C28) -> 0 | R28: =(R12*$B28)+(R12*$C28) -> 0 | S28: =(S12*$B28)+(S12*$C28) -> 0 | T28: =(T12*$B28)+(T12*$C28) -> 0 | U28: =(U12*$B28)+(U12*$C28) -> 0 | V28: =(V12*$B28)+(V12*$C28) -> 0 | W28: =(W12*$B28)+(W12*$C28) -> 0 | X28: =(X12*$B28)+(X12*$C28) -> 0 | ... AB28: =(AB12*$B28)+(AB12*$C28) -> 0 | AC28: =SUM(Q28:AB28) -> 0 | AD28: =(AD12*$B28)+(AD12*$C28) -> 0 | AE28: =(AE12*$B28)+(AE12*$C28) -> 0 | AF28: =(AF12*$B28)+(AF12*$C28) -> 0 | AG28: =(AG12*$B28)+(AG12*$C28) -> 0 | AH28: =(AH12*$B28)+(AH12*$C28) -> 0 | AI28: =(AI12*$B28)+(AI12*$C28) -> 0 | AJ28: =(AJ12*$B28)+(AJ12*$C28) -> 0 | AK28: =(AK12*$B28)+(AK12*$C28) -> 0 | ... AO28: =(AO12*$B28)+(AO12*$C28) -> 0 | AP28: =SUM(AD28:AO28) -> 0
A29: Total Hours | D29: =SUM(D20:D28) -> 3071 | E29: =SUM(E20:E28) -> 3106.5 | F29: =SUM(F20:F28) -> 3142 | G29: =SUM(G20:G28) -> 3177.5 | H29: =SUM(H20:H28) -> 3177.5 | I29: =SUM(I20:I28) -> 3177.5 | J29: =SUM(J20:J28) -> 3213 | K29: =SUM(K20:K28) -> 3213 | ... AP29: =SUM(AP20:AP28) -> 38982
P30: =SUM(D30:O30) -> 0 | AC30: =SUM(Q30:AB30) -> 0 | AP30: =SUM(AD30:AO30) -> 0
A31: Labor Rates
A32: JSX Heavy Inspection | B32: 100 | D32: =D20*$B$32 -> 300000 | E32: =E20*$B$32 -> 300000 | F32: =F20*$B$32 -> 300000 | G32: =G20*$B$32 -> 300000 | H32: =H20*$B$32 -> 300000 | I32: =I20*$B$32 -> 300000 | J32: =J20*$B$32 -> 300000 | K32: =K20*$B$32 -> 300000 | ... O32: =O20*$B$32 -> 300000 | P32: =SUM(D32:O32) -> 3600000 | Q32: =Q20*$B$32 -> 300000 | R32: =R20*$B$32 -> 300000 | S32: =S20*$B$32 -> 300000 | T32: =T20*$B$32 -> 300000 | U32: =U20*$B$32 -> 300000 | V32: =V20*$B$32 -> 0 | W32: =W20*$B$32 -> 300000 | X32: =X20*$B$32 -> 300000 | ... AB32: =AB20*$B$32 -> 0 | AC32: =SUM(Q32:AB32) -> 3000000 | AD32: =AD20*$B$32 -> 300000 | AE32: =AE20*$B$32 -> 300000 | AF32: =AF20*$B$32 -> 300000 | AG32: =AG20*$B$32 -> 300000 | AH32: =AH20*$B$32 -> 300000 | AI32: =AI20*$B$32 -> 300000 | AJ32: =AJ20*$B$32 -> 300000 | AK32: =AK20*$B$32 -> 300000 | ... AO32: =AO20*$B$32 -> 300000 | AP32: =SUM(AD32:AO32) -> 3600000
A33: JSX Line Check | B33: 500 | D33: =D21*$B$32 -> 4800 | E33: =E21*$B$32 -> 7200 | F33: =F21*$B$32 -> 9600 | G33: =G21*$B$32 -> 12000 | H33: =H21*$B$32 -> 12000 | I33: =I21*$B$32 -> 12000 | J33: =J21*$B$32 -> 14400 | K33: =K21*$B$32 -> 14400 | ... O33: =O21*$B$32 -> 16800 | P33: =SUM(D33:O33) -> 153600 | Q33: =Q21*$B$32 -> 16800 | R33: =R21*$B$32 -> 16800 | S33: =S21*$B$32 -> 16800 | T33: =T21*$B$32 -> 16800 | U33: =U21*$B$32 -> 16800 | V33: =V21*$B$32 -> 16800 | W33: =W21*$B$32 -> 16800 | X33: =X21*$B$32 -> 16800 | ... AB33: =AB21*$B$32 -> 16800 | AC33: =SUM(Q33:AB33) -> 201600 | AD33: =AD21*$B$32 -> 16800 | AE33: =AE21*$B$32 -> 16800 | AF33: =AF21*$B$32 -> 16800 | AG33: =AG21*$B$32 -> 16800 | AH33: =AH21*$B$32 -> 16800 | AI33: =AI21*$B$32 -> 16800 | AJ33: =AJ21*$B$32 -> 16800 | AK33: =AK21*$B$32 -> 16800 | ... AO33: =AO21*$B$32 -> 16800 | AP33: =SUM(AD33:AO33) -> 201600
A34: JSX First Flight of the day | B34: 130 | D34: =D22*$B$32 -> 300 | E34: =E22*$B$32 -> 450 | F34: =F22*$B$32 -> 600 | G34: =G22*$B$32 -> 750 | H34: =H22*$B$32 -> 750 | I34: =I22*$B$32 -> 750 | J34: =J22*$B$32 -> 900 | K34: =K22*$B$32 -> 900 | ... O34: =O22*$B$32 -> 1050 | Q34: =Q22*$B$32 -> 1050 | R34: =R22*$B$32 -> 1050 | S34: =S22*$B$32 -> 1050 | T34: =T22*$B$32 -> 1050 | U34: =U22*$B$32 -> 1050 | V34: =V22*$B$32 -> 1050 | W34: =W22*$B$32 -> 1050 | X34: =X22*$B$32 -> 1050 | ... AB34: =AB22*$B$32 -> 1050 | AD34: =AD22*$B$32 -> 1050 | AE34: =AE22*$B$32 -> 1050 | AF34: =AF22*$B$32 -> 1050 | AG34: =AG22*$B$32 -> 1050 | AH34: =AH22*$B$32 -> 1050 | AI34: =AI22*$B$32 -> 1050 | AJ34: =AJ22*$B$32 -> 1050 | AK34: =AK22*$B$32 -> 1050 | ... AO34: =AO22*$B$32 -> 1050
A35: JSX AOG MX | B35: 195 | D35: =D23*$B$32 -> 2000 | E35: =E23*$B$32 -> 3000 | F35: =F23*$B$32 -> 4000 | G35: =G23*$B$32 -> 5000 | H35: =H23*$B$32 -> 5000 | I35: =I23*$B$32 -> 5000 | J35: =J23*$B$32 -> 6000 | K35: =K23*$B$32 -> 6000 | ... O35: =O23*$B$32 -> 7000 | Q35: =Q23*$B$32 -> 7000 | R35: =R23*$B$32 -> 7000 | S35: =S23*$B$32 -> 7000 | T35: =T23*$B$32 -> 7000 | U35: =U23*$B$32 -> 7000 | V35: =V23*$B$32 -> 7000 | W35: =W23*$B$32 -> 7000 | X35: =X23*$B$32 -> 7000 | ... AB35: =AB23*$B$32 -> 7000 | AD35: =AD23*$B$32 -> 7000 | AE35: =AE23*$B$32 -> 7000 | AF35: =AF23*$B$32 -> 7000 | AG35: =AG23*$B$32 -> 7000 | AH35: =AH23*$B$32 -> 7000 | AI35: =AI23*$B$32 -> 7000 | AJ35: =AJ23*$B$32 -> 7000 | AK35: =AK23*$B$32 -> 7000 | ... AO35: =AO23*$B$32 -> 7000
A36: Retail MX | B36: 169 | D36: =D24*$B$32 -> 0 | E36: =E24*$B$32 -> 0 | F36: =F24*$B$32 -> 0 | G36: =G24*$B$32 -> 0 | H36: =H24*$B$32 -> 0 | I36: =I24*$B$32 -> 0 | J36: =J24*$B$32 -> 0 | K36: =K24*$B$32 -> 0 | ... O36: =O24*$B$32 -> 0 | Q36: =Q24*$B$32 -> 0 | R36: =R24*$B$32 -> 0 | S36: =S24*$B$32 -> 0 | T36: =T24*$B$32 -> 0 | U36: =U24*$B$32 -> 0 | V36: =V24*$B$32 -> 0 | W36: =W24*$B$32 -> 0 | X36: =X24*$B$32 -> 0 | ... AB36: =AB24*$B$32 -> 0 | AD36: =AD24*$B$32 -> 0 | AE36: =AE24*$B$32 -> 0 | AF36: =AF24*$B$32 -> 0 | AG36: =AG24*$B$32 -> 0 | AH36: =AH24*$B$32 -> 0 | AI36: =AI24*$B$32 -> 0 | AJ36: =AJ24*$B$32 -> 0 | AK36: =AK24*$B$32 -> 0 | ... AO36: =AO24*$B$32 -> 0
A37: Retail AOG | B37: 254 | D37: =D25*$B$32 -> 0 | E37: =E25*$B$32 -> 0 | F37: =F25*$B$32 -> 0 | G37: =G25*$B$32 -> 0 | H37: =H25*$B$32 -> 0 | I37: =I25*$B$32 -> 0 | J37: =J25*$B$32 -> 0 | K37: =K25*$B$32 -> 0 | ... O37: =O25*$B$32 -> 0 | Q37: =Q25*$B$32 -> 0 | R37: =R25*$B$32 -> 0 | S37: =S25*$B$32 -> 0 | T37: =T25*$B$32 -> 0 | U37: =U25*$B$32 -> 0 | V37: =V25*$B$32 -> 0 | W37: =W25*$B$32 -> 0 | X37: =X25*$B$32 -> 0 | ... AB37: =AB25*$B$32 -> 0 | AD37: =AD25*$B$32 -> 0 | AE37: =AE25*$B$32 -> 0 | AF37: =AF25*$B$32 -> 0 | AG37: =AG25*$B$32 -> 0 | AH37: =AH25*$B$32 -> 0 | AI37: =AI25*$B$32 -> 0 | AJ37: =AJ25*$B$32 -> 0 | AK37: =AK25*$B$32 -> 0 | ... AO37: =AO25*$B$32 -> 0
A38: Placeholder | D38: =D26*$B$32 -> 0 | E38: =E26*$B$32 -> 0 | F38: =F26*$B$32 -> 0 | G38: =G26*$B$32 -> 0 | H38: =H26*$B$32 -> 0 | I38: =I26*$B$32 -> 0 | J38: =J26*$B$32 -> 0 | K38: =K26*$B$32 -> 0 | ... O38: =O26*$B$32 -> 0 | Q38: =Q26*$B$32 -> 0 | R38: =R26*$B$32 -> 0 | S38: =S26*$B$32 -> 0 | T38: =T26*$B$32 -> 0 | U38: =U26*$B$32 -> 0 | V38: =V26*$B$32 -> 0 | W38: =W26*$B$32 -> 0 | X38: =X26*$B$32 -> 0 | ... AB38: =AB26*$B$32 -> 0 | AD38: =AD26*$B$32 -> 0 | AE38: =AE26*$B$32 -> 0 | AF38: =AF26*$B$32 -> 0 | AG38: =AG26*$B$32 -> 0 | AH38: =AH26*$B$32 -> 0 | AI38: =AI26*$B$32 -> 0 | AJ38: =AJ26*$B$32 -> 0 | AK38: =AK26*$B$32 -> 0 | ... AO38: =AO26*$B$32 -> 0
A39: Placeholder | D39: =D27*$B$32 -> 0 | E39: =E27*$B$32 -> 0 | F39: =F27*$B$32 -> 0 | G39: =G27*$B$32 -> 0 | H39: =H27*$B$32 -> 0 | I39: =I27*$B$32 -> 0 | J39: =J27*$B$32 -> 0 | K39: =K27*$B$32 -> 0 | ... O39: =O27*$B$32 -> 0 | Q39: =Q27*$B$32 -> 0 | R39: =R27*$B$32 -> 0 | S39: =S27*$B$32 -> 0 | T39: =T27*$B$32 -> 0 | U39: =U27*$B$32 -> 0 | V39: =V27*$B$32 -> 0 | W39: =W27*$B$32 -> 0 | X39: =X27*$B$32 -> 0 | ... AB39: =AB27*$B$32 -> 0 | AD39: =AD27*$B$32 -> 0 | AE39: =AE27*$B$32 -> 0 | AF39: =AF27*$B$32 -> 0 | AG39: =AG27*$B$32 -> 0 | AH39: =AH27*$B$32 -> 0 | AI39: =AI27*$B$32 -> 0 | AJ39: =AJ27*$B$32 -> 0 | AK39: =AK27*$B$32 -> 0 | ... AO39: =AO27*$B$32 -> 0
A40: Placeholder | D40: =D28*$B$32 -> 0 | E40: =E28*$B$32 -> 0 | F40: =F28*$B$32 -> 0 | G40: =G28*$B$32 -> 0 | H40: =H28*$B$32 -> 0 | I40: =I28*$B$32 -> 0 | J40: =J28*$B$32 -> 0 | K40: =K28*$B$32 -> 0 | ... O40: =O28*$B$32 -> 0 | Q40: =Q28*$B$32 -> 0 | R40: =R28*$B$32 -> 0 | S40: =S28*$B$32 -> 0 | T40: =T28*$B$32 -> 0 | U40: =U28*$B$32 -> 0 | V40: =V28*$B$32 -> 0 | W40: =W28*$B$32 -> 0 | X40: =X28*$B$32 -> 0 | ... AB40: =AB28*$B$32 -> 0 | AD40: =AD28*$B$32 -> 0 | AE40: =AE28*$B$32 -> 0 | AF40: =AF28*$B$32 -> 0 | AG40: =AG28*$B$32 -> 0 | AH40: =AH28*$B$32 -> 0 | AI40: =AI28*$B$32 -> 0 | AJ40: =AJ28*$B$32 -> 0 | AK40: =AK28*$B$32 -> 0 | ... AO40: =AO28*$B$32 -> 0
A41: Total Revenue | D41: =SUM(D32:D40) -> 307100 | E41: =SUM(E32:E40) -> 310650 | F41: =SUM(F32:F40) -> 314200 | G41: =SUM(G32:G40) -> 317750 | H41: =SUM(H32:H40) -> 317750 | I41: =SUM(I32:I40) -> 317750 | J41: =SUM(J32:J40) -> 321300 | K41: =SUM(K32:K40) -> 321300 | ... O41: =SUM(O32:O40) -> 324850 | P41: =SUM(D41:O41) -> 3827200 | Q41: =SUM(Q32:Q40) -> 324850 | R41: =SUM(R32:R40) -> 324850 | S41: =SUM(S32:S40) -> 324850 | T41: =SUM(T32:T40) -> 324850 | U41: =SUM(U32:U40) -> 324850 | V41: =SUM(V32:V40) -> 24850 | W41: =SUM(W32:W40) -> 324850 | X41: =SUM(X32:X40) -> 324850 | ... AB41: =SUM(AB32:AB40) -> 24850 | AC41: =SUM(Q41:AB41) -> 3298200 | AD41: =SUM(AD32:AD40) -> 324850 | AE41: =SUM(AE32:AE40) -> 324850 | AF41: =SUM(AF32:AF40) -> 324850 | AG41: =SUM(AG32:AG40) -> 324850 | AH41: =SUM(AH32:AH40) -> 324850 | AI41: =SUM(AI32:AI40) -> 324850 | AJ41: =SUM(AJ32:AJ40) -> 324850 | AK41: =SUM(AK32:AK40) -> 324850 | ... AO41: =SUM(AO32:AO40) -> 324850 | AP41: =SUM(AD41:AO41) -> 3898200
A43: Effective Techs | D43: ='Man Hours & Costs'!C18 -> 20.8 | E43: ='Man Hours & Costs'!D18 -> 20.8 | F43: ='Man Hours & Costs'!E18 -> 20.8 | G43: ='Man Hours & Costs'!F18 -> 20.8 | H43: ='Man Hours & Costs'!G18 -> 20.8 | I43: ='Man Hours & Costs'!H18 -> 20.8 | J43: ='Man Hours & Costs'!I18 -> 20.8 | K43: ='Man Hours & Costs'!J18 -> 20.8 | ... O43: ='Man Hours & Costs'!N18 -> 20.8 | Q43: ='Man Hours & Costs'!P18 -> 24 | R43: ='Man Hours & Costs'!Q18 -> 28.8 | S43: ='Man Hours & Costs'!R18 -> 28.8 | T43: ='Man Hours & Costs'!S18 -> 28.8 | U43: ='Man Hours & Costs'!T18 -> 28.8 | V43: ='Man Hours & Costs'!U18 -> 28.8 | W43: ='Man Hours & Costs'!V18 -> 28.8 | X43: ='Man Hours & Costs'!W18 -> 24 | ... AB43: ='Man Hours & Costs'!AA18 -> 24 | AD43: ='Man Hours & Costs'!AC18 -> 24 | AE43: ='Man Hours & Costs'!AD18 -> 24 | AF43: ='Man Hours & Costs'!AE18 -> 24 | AG43: ='Man Hours & Costs'!AF18 -> 24 | AH43: ='Man Hours & Costs'!AG18 -> 24 | AI43: ='Man Hours & Costs'!AH18 -> 24 | AJ43: ='Man Hours & Costs'!AI18 -> 24 | AK43: ='Man Hours & Costs'!AJ18 -> 24 | ... AO43: ='Man Hours & Costs'!AN18 -> 24
A44: Billable hours free | D44: ='Man Hours & Costs'!C20 -> 3260.192 | E44: ='Man Hours & Costs'!D20 -> 3095.04 | F44: ='Man Hours & Costs'!E20 -> 3590.496 | G44: ='Man Hours & Costs'!F20 -> 3095.04 | H44: ='Man Hours & Costs'!G20 -> 3425.344 | I44: ='Man Hours & Costs'!H20 -> 3425.344 | J44: ='Man Hours & Costs'!I20 -> 3095.04 | K44: ='Man Hours & Costs'!J20 -> 3590.496 | ... O44: ='Man Hours & Costs'!N20 -> 2434.432 | P44: =SUM(D44:O44) -> 38626.848 | Q44: ='Man Hours & Costs'!P20 -> 3761.76 | R44: ='Man Hours & Costs'!Q20 -> 4285.44 | S44: ='Man Hours & Costs'!R20 -> 4971.456 | T44: ='Man Hours & Costs'!S20 -> 4285.44 | U44: ='Man Hours & Costs'!T20 -> 4742.784 | V44: ='Man Hours & Costs'!U20 -> 4742.784 | W44: ='Man Hours & Costs'!V20 -> 4285.44 | X44: ='Man Hours & Costs'!W20 -> 4142.88 | ... AB44: ='Man Hours & Costs'!AA20 -> 2808.96 | AC44: =SUM(Q44:AB44) -> 49121.664 | AD44: ='Man Hours & Costs'!AC20 -> 3761.76 | AE44: ='Man Hours & Costs'!AD20 -> 3571.2 | AF44: ='Man Hours & Costs'!AE20 -> 4142.88 | AG44: ='Man Hours & Costs'!AF20 -> 3571.2 | AH44: ='Man Hours & Costs'!AG20 -> 3952.32 | AI44: ='Man Hours & Costs'!AH20 -> 3952.32 | AJ44: ='Man Hours & Costs'!AI20 -> 3571.2 | AK44: ='Man Hours & Costs'!AJ20 -> 4142.88 | ... AO44: ='Man Hours & Costs'!AN20 -> 2808.96 | AP44: =SUM(AD44:AO44) -> 44569.44
A45: Unused hours | D45: =D44-D29 -> 189.192 | E45: =E44-E29 -> -11.46 | F45: =F44-F29 -> 448.496 | G45: =G44-G29 -> -82.46 | H45: =H44-H29 -> 247.844 | I45: =I44-I29 -> 247.844 | J45: =J44-J29 -> -117.96 | K45: =K44-K29 -> 377.496 | ... AP45: =AP44-AP29 -> 5587.44
A46: Unused capacity % | D46: =D45/D44 -> 0.058030938 | E46: =E45/E44 -> -0.0037026985 | F46: =F45/F44 -> 0.12491199 | G46: =G45/G44 -> -0.026642628 | H46: =H45/H44 -> 0.072355944 | I46: =I45/I44 -> 0.072355944 | J46: =J45/J44 -> -0.038112593 | K46: =K45/K44 -> 0.10513756 | ... O46: =O45/O44 -> -0.33439751 | Q46: =Q45/Q44 -> 0.13644145 | R46: =R45/R44 -> 0.24196815 | S46: =S45/S44 -> 0.3465697 | T46: =T45/T44 -> 0.24196815 | U46: =U45/U44 -> 0.31506474 | V46: =V45/V44 -> 0.94760461 | W46: =W45/W44 -> 0.24196815 | X46: =X45/X44 -> 0.21588364 | ... AO46: =AO45/AO44 -> -0.15647784
A48: Total Cost of Labor | D48: ='Man Hours & Costs'!C34 -> -246486.24 | E48: ='Man Hours & Costs'!D34 -> -234748.8 | F48: ='Man Hours & Costs'!E34 -> -269961.12 | G48: ='Man Hours & Costs'!F34 -> -234748.8 | H48: ='Man Hours & Costs'!G34 -> -258223.68 | I48: ='Man Hours & Costs'!H34 -> -258223.68 | J48: ='Man Hours & Costs'!I34 -> -234748.8 | K48: ='Man Hours & Costs'!J34 -> -269961.12 | ... O48: ='Man Hours & Costs'!N34 -> -187799.04 | P48: =SUM(D48:O48) -> -2922622.6 | Q48: ='Man Hours & Costs'!P34 -> -284407.2 | R48: ='Man Hours & Costs'!Q34 -> -325036.8 | S48: ='Man Hours & Costs'!R34 -> -373792.32 | T48: ='Man Hours & Costs'!S34 -> -325036.8 | U48: ='Man Hours & Costs'!T34 -> -357540.48 | V48: ='Man Hours & Costs'!U34 -> -357540.48 | W48: ='Man Hours & Costs'!V34 -> -325036.8 | X48: ='Man Hours & Costs'!W34 -> -311493.6 | ... AB48: ='Man Hours & Costs'!AA34 -> -216691.2 | AC48: =SUM(Q48:AB48) -> -3716254.1 | AD48: ='Man Hours & Costs'!AC34 -> -284407.2 | AE48: ='Man Hours & Costs'!AD34 -> -270864 | AF48: ='Man Hours & Costs'!AE34 -> -311493.6 | AG48: ='Man Hours & Costs'!AF34 -> -270864 | AH48: ='Man Hours & Costs'!AG34 -> -297950.4 | AI48: ='Man Hours & Costs'!AH34 -> -297950.4 | AJ48: ='Man Hours & Costs'!AI34 -> -270864 | AK48: ='Man Hours & Costs'!AJ34 -> -311493.6 | ... AO48: ='Man Hours & Costs'!AN34 -> -216691.2 | AP48: =SUM(AD48:AO48) -> -3372256.8
A49: Hanger 4 | P49: =SUM(D49:O49) -> 0 | AC49: =SUM(Q49:AB49) -> 0 | AP49: =SUM(AD49:AO49) -> 0
A50: Training | P50: =SUM(D50:O50) -> 0 | AC50: =SUM(Q50:AB50) -> 0 | AP50: =SUM(AD50:AO50) -> 0
A51: Saftey Investments | P51: =SUM(D51:O51) -> 0 | AC51: =SUM(Q51:AB51) -> 0 | AP51: =SUM(AD51:AO51) -> 0
A52: Tooling investments | P52: =SUM(D52:O52) -> 0 | AC52: =SUM(Q52:AB52) -> 0 | AP52: =SUM(AD52:AO52) -> 0
A53: Shop investments | P53: =SUM(D53:O53) -> 0 | AC53: =SUM(Q53:AB53) -> 0 | AP53: =SUM(AD53:AO53) -> 0
A54: Marketing | P54: =SUM(E54:O54) -> 0 | AC54: =SUM(R54:AB54) -> 0 | AP54: =SUM(AD54:AO54) -> 0
A55: Recruting | P55: =SUM(E55:O55) -> 0 | AC55: =SUM(R55:AB55) -> 0 | AP55: =SUM(AE55:AO55) -> 0
A56: Facilities Main hangar | P56: =SUM(E56:O56) -> 0 | AC56: =SUM(R56:AB56) -> 0 | AP56: =SUM(AE56:AO56) -> 0
A57: Facilities AUX Hangar | P57: =SUM(E57:O57) -> 0 | AC57: =SUM(R57:AB57) -> 0 | AP57: =SUM(AE57:AO57) -> 0
A58: Rennovations | P58: =SUM(E58:O58) -> 0 | AC58: =SUM(R58:AB58) -> 0 | AP58: =SUM(AE58:AO58) -> 0
A59: Bonuses | P59: =SUM(E59:O59) -> 0 | AC59: =SUM(R59:AB59) -> 0 | AP59: =SUM(AE59:AO59) -> 0
A60: Tool allowance | B60: =Controls!D70 -> -125 | P60: =SUM(E60:O60) -> 0 | AC60: =SUM(R60:AB60) -> 0 | AP60: =SUM(AE60:AO60) -> 0
A61: Total Costs | D61: =SUM(D48:D60) -> -246486.24 | E61: =SUM(E48:E60) -> -234748.8 | F61: =SUM(F48:F60) -> -269961.12 | G61: =SUM(G48:G60) -> -234748.8 | H61: =SUM(H48:H60) -> -258223.68 | I61: =SUM(I48:I60) -> -258223.68 | J61: =SUM(J48:J60) -> -234748.8 | K61: =SUM(K48:K60) -> -269961.12 | ... O61: =SUM(O48:O60) -> -187799.04 | P61: =SUM(D61:O61) -> -2922622.6 | Q61: =SUM(Q48:Q60) -> -284407.2 | R61: =SUM(R48:R60) -> -325036.8 | S61: =SUM(S48:S60) -> -373792.32 | T61: =SUM(T48:T60) -> -325036.8 | U61: =SUM(U48:U60) -> -357540.48 | V61: =SUM(V48:V60) -> -357540.48 | W61: =SUM(W48:W60) -> -325036.8 | X61: =SUM(X48:X60) -> -311493.6 | ... AB61: =SUM(AB48:AB60) -> -216691.2 | AC61: =SUM(Q61:AB61) -> -3716254.1 | AD61: =SUM(AD48:AD60) -> -284407.2 | AE61: =SUM(AE48:AE60) -> -270864 | AF61: =SUM(AF48:AF60) -> -311493.6 | AG61: =SUM(AG48:AG60) -> -270864 | AH61: =SUM(AH48:AH60) -> -297950.4 | AI61: =SUM(AI48:AI60) -> -297950.4 | AJ61: =SUM(AJ48:AJ60) -> -270864 | AK61: =SUM(AK48:AK60) -> -311493.6 | ... AO61: =SUM(AO48:AO60) -> -216691.2 | AP61: =SUM(AD61:AO61) -> -3372256.8
A63: Gross Profit | D63: =SUM(D41,D61) -> 60613.76 | E63: =SUM(E41,E61) -> 75901.2 | F63: =SUM(F41,F61) -> 44238.88 | G63: =SUM(G41,G61) -> 83001.2 | H63: =SUM(H41,H61) -> 59526.32 | I63: =SUM(I41,I61) -> 59526.32 | J63: =SUM(J41,J61) -> 86551.2 | K63: =SUM(K41,K61) -> 51338.88 | ... O63: =SUM(O41,O61) -> 137050.96 | P63: =SUM(D63:O63) -> 904577.44 | Q63: =SUM(Q41,Q61) -> 40442.8 | R63: =SUM(R41,R61) -> -186.8 | S63: =SUM(S41,S61) -> -48942.32 | T63: =SUM(T41,T61) -> -186.8 | U63: =SUM(U41,U61) -> -32690.48 | V63: =SUM(V41,V61) -> -332690.48 | W63: =SUM(W41,W61) -> -186.8 | X63: =SUM(X41,X61) -> 13356.4 | ... AB63: =SUM(AB41,AB61) -> -191841.2 | AC63: =SUM(Q63:AB63) -> -418054.08 | AD63: =SUM(AD41,AD61) -> 40442.8 | AE63: =SUM(AE41,AE61) -> 53986 | AF63: =SUM(AF41,AF61) -> 13356.4 | AG63: =SUM(AG41,AG61) -> 53986 | AH63: =SUM(AH41,AH61) -> 26899.6 | AI63: =SUM(AI41,AI61) -> 26899.6 | AJ63: =SUM(AJ41,AJ61) -> 53986 | AK63: =SUM(AK41,AK61) -> 13356.4 | ... AO63: =SUM(AO41,AO61) -> 108158.8 | AP63: =SUM(AD63:AO63) -> 525943.2
A65: Total Free Cash Flow | D65: =SUM(D41,D61) -> 60613.76 | E65: =SUM(E41,E61) -> 75901.2 | F65: =SUM(F41,F61) -> 44238.88 | G65: =SUM(G41,G61) -> 83001.2 | H65: =SUM(H41,H61) -> 59526.32 | I65: =SUM(I41,I61) -> 59526.32 | J65: =SUM(J41,J61) -> 86551.2 | K65: =SUM(K41,K61) -> 51338.88 | ... O65: =SUM(O41,O61) -> 137050.96 | P65: =SUM(D65:O65) -> 904577.44 | Q65: =SUM(Q41,Q61) -> 40442.8 | R65: =SUM(R41,R61) -> -186.8 | S65: =SUM(S41,S61) -> -48942.32 | T65: =SUM(T41,T61) -> -186.8 | U65: =SUM(U41,U61) -> -32690.48 | V65: =SUM(V41,V61) -> -332690.48 | W65: =SUM(W41,W61) -> -186.8 | X65: =SUM(X41,X61) -> 13356.4 | ... AB65: =SUM(AB41,AB61) -> -191841.2 | AC65: =SUM(Q65:AB65) -> -418054.08 | AD65: =SUM(AD41,AD61) -> 40442.8 | AE65: =SUM(AE41,AE61) -> 53986 | AF65: =SUM(AF41,AF61) -> 13356.4 | AG65: =SUM(AG41,AG61) -> 53986 | AH65: =SUM(AH41,AH61) -> 26899.6 | AI65: =SUM(AI41,AI61) -> 26899.6 | AJ65: =SUM(AJ41,AJ61) -> 53986 | AK65: =SUM(AK41,AK61) -> 13356.4 | ... AO65: =SUM(AO41,AO61) -> 108158.8 | AP65: =SUM(AD65:AO65) -> 525943.2
A66: Rolling Sum | D66: =D65 -> 60613.76 | E66: =D66+E65 -> 136514.96 | F66: =E66+F65 -> 180753.84 | G66: =F66+G65 -> 263755.04 | H66: =G66+H65 -> 323281.36 | I66: =H66+I65 -> 382807.68 | J66: =I66+J65 -> 469358.88 | K66: =J66+K65 -> 520697.76 | L66: =K66+L65 -> 610798.96 | ... O66: =N66+O65 -> 904577.44 | Q66: =O66+Q65 -> 945020.24 | R66: =Q66+R65 -> 944833.44 | S66: =R66+S65 -> 895891.12 | T66: =S66+T65 -> 895704.32 | U66: =T66+U65 -> 863013.84 | V66: =U66+V65 -> 530323.36 | W66: =V66+W65 -> 530136.56 | X66: =W66+X65 -> 543492.96 | Y66: =X66+Y65 -> 597478.96 | ... AB66: =AA66+AB65 -> 486523.36 | AD66: =AB66+AD65 -> 526966.16 | AE66: =AD66+AE65 -> 580952.16 | AF66: =AE66+AF65 -> 594308.56 | AG66: =AF66+AG65 -> 648294.56 | AH66: =AG66+AH65 -> 675194.16 | AI66: =AH66+AI65 -> 702093.76 | AJ66: =AI66+AJ65 -> 756079.76 | AK66: =AJ66+AK65 -> 769436.16 | AL66: =AK66+AL65 -> 823422.16 | ... AO66: =AN66+AO65 -> 1012466.6

Sheet Visualization
B116: ='2023 Forecast Totals'!D$3 -> Jan | C116: ='2023 Forecast Totals'!E$3 -> Feb | D116: ='2023 Forecast Totals'!F$3 -> Mar | E116: ='2023 Forecast Totals'!G$3 -> Apr | F116: ='2023 Forecast Totals'!H$3 -> May | G116: ='2023 Forecast Totals'!I$3 -> Jun | H116: ='2023 Forecast Totals'!J$3 -> Jul | I116: ='2023 Forecast Totals'!K$3 -> Aug | ... M116: ='2023 Forecast Totals'!O$3 -> Dec
A117: =TEAMGROWTH!D27 -> Avionics lead | B117: =TEAMGROWTH!L27 -> 164.56825 | C117: =TEAMGROWTH!N27 -> 164.56825 | D117: =TEAMGROWTH!P27 -> 164.56825 | E117: =TEAMGROWTH!R27 -> 164.56825 | F117: =TEAMGROWTH!T27 -> 164.56825 | G117: =TEAMGROWTH!V27 -> 164.56825 | H117: =TEAMGROWTH!X27 -> 164.56825 | I117: =TEAMGROWTH!Z27 -> 164.56825 | J117: =TEAMGROWTH!AB27 -> 164.56825 | K117: =TEAMGROWTH!AD27 -> 164.56825 | L117: =TEAMGROWTH!AF27 -> 164.56825 | M117: =TEAMGROWTH!AH27 -> 164.56825
A118: =TEAMGROWTH!D28 -> Lead | B118: =TEAMGROWTH!L28 -> 82.284125 | C118: =TEAMGROWTH!N28 -> 82.284125 | D118: =TEAMGROWTH!P28 -> 82.284125 | E118: =TEAMGROWTH!R28 -> 82.284125 | F118: =TEAMGROWTH!T28 -> 82.284125 | G118: =TEAMGROWTH!V28 -> 82.284125 | H118: =TEAMGROWTH!X28 -> 82.284125 | I118: =TEAMGROWTH!Z28 -> 82.284125 | J118: =TEAMGROWTH!AB28 -> 82.284125 | K118: =TEAMGROWTH!AD28 -> 82.284125 | L118: =TEAMGROWTH!AF28 -> 82.284125 | M118: =TEAMGROWTH!AH28 -> 82.284125
A119: =TEAMGROWTH!D29 -> Joe Vigil AP/AV | B119: =TEAMGROWTH!L29 -> 164.56825 | C119: =TEAMGROWTH!N29 -> 164.56825 | D119: =TEAMGROWTH!P29 -> 164.56825 | E119: =TEAMGROWTH!R29 -> 164.56825 | F119: =TEAMGROWTH!T29 -> 164.56825 | G119: =TEAMGROWTH!V29 -> 164.56825 | H119: =TEAMGROWTH!X29 -> 164.56825 | I119: =TEAMGROWTH!Z29 -> 164.56825 | J119: =TEAMGROWTH!AB29 -> 164.56825 | K119: =TEAMGROWTH!AD29 -> 164.56825 | L119: =TEAMGROWTH!AF29 -> 164.56825 | M119: =TEAMGROWTH!AH29 -> 164.56825
A120: =TEAMGROWTH!D30 -> X Mech 1, 1-3YR AP | B120: =TEAMGROWTH!L30 -> 115.19777 | C120: =TEAMGROWTH!N30 -> 143.99722 | D120: =TEAMGROWTH!P30 -> 164.56825 | E120: =TEAMGROWTH!R30 -> 164.56825 | F120: =TEAMGROWTH!T30 -> 164.56825 | G120: =TEAMGROWTH!V30 -> 164.56825 | H120: =TEAMGROWTH!X30 -> 164.56825 | I120: =TEAMGROWTH!Z30 -> 164.56825 | J120: =TEAMGROWTH!AB30 -> 164.56825 | K120: =TEAMGROWTH!AD30 -> 164.56825 | L120: =TEAMGROWTH!AF30 -> 164.56825 | M120: =TEAMGROWTH!AH30 -> 164.56825
A121: =TEAMGROWTH!D31 -> X Mech 2, 1-3YR Entry AP | B121: =TEAMGROWTH!L31 -> 115.19777 | C121: =TEAMGROWTH!N31 -> 143.99722 | D121: =TEAMGROWTH!P31 -> 164.56825 | E121: =TEAMGROWTH!R31 -> 164.56825 | F121: =TEAMGROWTH!T31 -> 164.56825 | G121: =TEAMGROWTH!V31 -> 164.56825 | H121: =TEAMGROWTH!X31 -> 164.56825 | I121: =TEAMGROWTH!Z31 -> 164.56825 | J121: =TEAMGROWTH!AB31 -> 164.56825 | K121: =TEAMGROWTH!AD31 -> 164.56825 | L121: =TEAMGROWTH!AF31 -> 164.56825 | M121: =TEAMGROWTH!AH31 -> 164.56825
A122: =TEAMGROWTH!D32 -> X Mech 3, Entry AP | B122: =TEAMGROWTH!L32 -> 115.19777 | C122: =TEAMGROWTH!N32 -> 143.99722 | D122: =TEAMGROWTH!P32 -> 164.56825 | E122: =TEAMGROWTH!R32 -> 164.56825 | F122: =TEAMGROWTH!T32 -> 164.56825 | G122: =TEAMGROWTH!V32 -> 164.56825 | H122: =TEAMGROWTH!X32 -> 164.56825 | I122: =TEAMGROWTH!Z32 -> 164.56825 | J122: =TEAMGROWTH!AB32 -> 164.56825 | K122: =TEAMGROWTH!AD32 -> 164.56825 | L122: =TEAMGROWTH!AF32 -> 164.56825 | M122: =TEAMGROWTH!AH32 -> 164.56825
A123: =TEAMGROWTH!D33 -> X Mech 4, Entry AP | B123: =TEAMGROWTH!L33 -> 98.74095 | C123: =TEAMGROWTH!N33 -> 115.19777 | D123: =TEAMGROWTH!P33 -> 143.99722 | E123: =TEAMGROWTH!R33 -> 164.56825 | F123: =TEAMGROWTH!T33 -> 164.56825 | G123: =TEAMGROWTH!V33 -> 164.56825 | H123: =TEAMGROWTH!X33 -> 164.56825 | I123: =TEAMGROWTH!Z33 -> 164.56825 | J123: =TEAMGROWTH!AB33 -> 164.56825 | K123: =TEAMGROWTH!AD33 -> 164.56825 | L123: =TEAMGROWTH!AF33 -> 164.56825 | M123: =TEAMGROWTH!AH33 -> 164.56825
A124: =TEAMGROWTH!D34 -> Detailer and line support | B124: =TEAMGROWTH!L34 -> 49.370475 | C124: =TEAMGROWTH!N34 -> 49.370475 | D124: =TEAMGROWTH!P34 -> 49.370475 | E124: =TEAMGROWTH!R34 -> 49.370475 | F124: =TEAMGROWTH!T34 -> 49.370475 | G124: =TEAMGROWTH!V34 -> 49.370475 | H124: =TEAMGROWTH!X34 -> 49.370475 | I124: =TEAMGROWTH!Z34 -> 49.370475 | J124: =TEAMGROWTH!AB34 -> 49.370475 | K124: =TEAMGROWTH!AD34 -> 49.370475 | L124: =TEAMGROWTH!AF34 -> 49.370475 | M124: =TEAMGROWTH!AH34 -> 49.370475
A125: =TEAMGROWTH!#REF! -> #REF! | B125: =TEAMGROWTH!#REF! -> #REF! | C125: =TEAMGROWTH!#REF! -> #REF! | D125: =TEAMGROWTH!#REF! -> #REF! | E125: =TEAMGROWTH!#REF! -> #REF! | F125: =TEAMGROWTH!#REF! -> #REF! | G125: =TEAMGROWTH!#REF! -> #REF! | H125: =TEAMGROWTH!#REF! -> #REF! | ... M125: =TEAMGROWTH!#REF! -> #REF!
A126: =TEAMGROWTH!#REF! -> #REF! | B126: =TEAMGROWTH!#REF! -> #REF! | C126: =TEAMGROWTH!#REF! -> #REF! | D126: =TEAMGROWTH!#REF! -> #REF! | E126: =TEAMGROWTH!#REF! -> #REF! | F126: =TEAMGROWTH!#REF! -> #REF! | G126: =TEAMGROWTH!#REF! -> #REF! | H126: =TEAMGROWTH!#REF! -> #REF! | ... M126: =TEAMGROWTH!#REF! -> #REF!
A127: =TEAMGROWTH!#REF! -> #REF! | B127: =TEAMGROWTH!#REF! -> #REF! | C127: =TEAMGROWTH!#REF! -> #REF! | D127: =TEAMGROWTH!#REF! -> #REF! | E127: =TEAMGROWTH!#REF! -> #REF! | F127: =TEAMGROWTH!#REF! -> #REF! | G127: =TEAMGROWTH!#REF! -> #REF! | H127: =TEAMGROWTH!#REF! -> #REF! | ... M127: =TEAMGROWTH!#REF! -> #REF!
A128: =TEAMGROWTH!#REF! -> #REF! | B128: =TEAMGROWTH!#REF! -> #REF! | C128: =TEAMGROWTH!#REF! -> #REF! | D128: =TEAMGROWTH!#REF! -> #REF! | E128: =TEAMGROWTH!#REF! -> #REF! | F128: =TEAMGROWTH!#REF! -> #REF! | G128: =TEAMGROWTH!#REF! -> #REF! | H128: =TEAMGROWTH!#REF! -> #REF! | ... M128: =TEAMGROWTH!#REF! -> #REF!
A129: =TEAMGROWTH!#REF! -> #REF! | B129: =TEAMGROWTH!#REF! -> #REF! | C129: =TEAMGROWTH!#REF! -> #REF! | D129: =TEAMGROWTH!#REF! -> #REF! | E129: =TEAMGROWTH!#REF! -> #REF! | F129: =TEAMGROWTH!#REF! -> #REF! | G129: =TEAMGROWTH!#REF! -> #REF! | H129: =TEAMGROWTH!#REF! -> #REF! | ... M129: =TEAMGROWTH!#REF! -> #REF!
A130: =TEAMGROWTH!#REF! -> #REF! | B130: =TEAMGROWTH!#REF! -> #REF! | C130: =TEAMGROWTH!#REF! -> #REF! | D130: =TEAMGROWTH!#REF! -> #REF! | E130: =TEAMGROWTH!#REF! -> #REF! | F130: =TEAMGROWTH!#REF! -> #REF! | G130: =TEAMGROWTH!#REF! -> #REF! | H130: =TEAMGROWTH!#REF! -> #REF! | ... M130: =TEAMGROWTH!#REF! -> #REF!
A131: =TEAMGROWTH!#REF! -> #REF! | B131: =TEAMGROWTH!#REF! -> #REF! | C131: =TEAMGROWTH!#REF! -> #REF! | D131: =TEAMGROWTH!#REF! -> #REF! | E131: =TEAMGROWTH!#REF! -> #REF! | F131: =TEAMGROWTH!#REF! -> #REF! | G131: =TEAMGROWTH!#REF! -> #REF! | H131: =TEAMGROWTH!#REF! -> #REF! | ... M131: =TEAMGROWTH!#REF! -> #REF!
A132: =TEAMGROWTH!#REF! -> #REF! | B132: =TEAMGROWTH!#REF! -> #REF! | C132: =TEAMGROWTH!#REF! -> #REF! | D132: =TEAMGROWTH!#REF! -> #REF! | E132: =TEAMGROWTH!#REF! -> #REF! | F132: =TEAMGROWTH!#REF! -> #REF! | G132: =TEAMGROWTH!#REF! -> #REF! | H132: =TEAMGROWTH!#REF! -> #REF! | ... M132: =TEAMGROWTH!#REF! -> #REF!
A133: =TEAMGROWTH!#REF! -> #REF! | B133: =TEAMGROWTH!#REF! -> #REF! | C133: =TEAMGROWTH!#REF! -> #REF! | D133: =TEAMGROWTH!#REF! -> #REF! | E133: =TEAMGROWTH!#REF! -> #REF! | F133: =TEAMGROWTH!#REF! -> #REF! | G133: =TEAMGROWTH!#REF! -> #REF! | H133: =TEAMGROWTH!#REF! -> #REF! | ... M133: =TEAMGROWTH!#REF! -> #REF!
A134: =TEAMGROWTH!#REF! -> #REF! | B134: =TEAMGROWTH!#REF! -> #REF! | C134: =TEAMGROWTH!#REF! -> #REF! | D134: =TEAMGROWTH!#REF! -> #REF! | E134: =TEAMGROWTH!#REF! -> #REF! | F134: =TEAMGROWTH!#REF! -> #REF! | G134: =TEAMGROWTH!#REF! -> #REF! | H134: =TEAMGROWTH!#REF! -> #REF! | ... M134: =TEAMGROWTH!#REF! -> #REF!
A135: =TEAMGROWTH!#REF! -> #REF! | B135: =TEAMGROWTH!#REF! -> #REF! | C135: =TEAMGROWTH!#REF! -> #REF! | D135: =TEAMGROWTH!#REF! -> #REF! | E135: =TEAMGROWTH!#REF! -> #REF! | F135: =TEAMGROWTH!#REF! -> #REF! | G135: =TEAMGROWTH!#REF! -> #REF! | H135: =TEAMGROWTH!#REF! -> #REF! | ... M135: =TEAMGROWTH!#REF! -> #REF!
B138: ='2023 Forecast Totals'!D$3 -> Jan | C138: ='2023 Forecast Totals'!E$3 -> Feb | D138: ='2023 Forecast Totals'!F$3 -> Mar | E138: ='2023 Forecast Totals'!G$3 -> Apr | F138: ='2023 Forecast Totals'!H$3 -> May | G138: ='2023 Forecast Totals'!I$3 -> Jun | H138: ='2023 Forecast Totals'!J$3 -> Jul | I138: ='2023 Forecast Totals'!K$3 -> Aug | ... M138: ='2023 Forecast Totals'!O$3 -> Dec
A139: =TEAMGROWTH!D58 -> Drew Sandoval | B139: =TEAMGROWTH!L58 -> 164.56825 | C139: =TEAMGROWTH!N58 -> 164.56825 | D139: =TEAMGROWTH!P58 -> 164.56825 | E139: =TEAMGROWTH!R58 -> 164.56825 | F139: =TEAMGROWTH!T58 -> 164.56825 | G139: =TEAMGROWTH!V58 -> 164.56825 | H139: =TEAMGROWTH!X58 -> 164.56825 | I139: =TEAMGROWTH!Z58 -> 164.56825 | J139: =TEAMGROWTH!AB58 -> 164.56825 | K139: =TEAMGROWTH!AD58 -> 164.56825 | L139: =TEAMGROWTH!AF58 -> 164.56825 | M139: =TEAMGROWTH!AH58 -> 164.56825
A140: =TEAMGROWTH!#REF! -> #REF! | B140: =TEAMGROWTH!#REF! -> #REF! | C140: =TEAMGROWTH!#REF! -> #REF! | D140: =TEAMGROWTH!#REF! -> #REF! | E140: =TEAMGROWTH!#REF! -> #REF! | F140: =TEAMGROWTH!#REF! -> #REF! | G140: =TEAMGROWTH!#REF! -> #REF! | H140: =TEAMGROWTH!#REF! -> #REF! | ... M140: =TEAMGROWTH!#REF! -> #REF!
A141: =TEAMGROWTH!#REF! -> #REF! | B141: =TEAMGROWTH!#REF! -> #REF! | C141: =TEAMGROWTH!#REF! -> #REF! | D141: =TEAMGROWTH!#REF! -> #REF! | E141: =TEAMGROWTH!#REF! -> #REF! | F141: =TEAMGROWTH!#REF! -> #REF! | G141: =TEAMGROWTH!#REF! -> #REF! | H141: =TEAMGROWTH!#REF! -> #REF! | ... M141: =TEAMGROWTH!#REF! -> #REF!
A142: =TEAMGROWTH!#REF! -> #REF! | B142: =TEAMGROWTH!#REF! -> #REF! | C142: =TEAMGROWTH!#REF! -> #REF! | D142: =TEAMGROWTH!#REF! -> #REF! | E142: =TEAMGROWTH!#REF! -> #REF! | F142: =TEAMGROWTH!#REF! -> #REF! | G142: =TEAMGROWTH!#REF! -> #REF! | H142: =TEAMGROWTH!#REF! -> #REF! | ... M142: =TEAMGROWTH!#REF! -> #REF!
A143: =TEAMGROWTH!#REF! -> #REF! | B143: =TEAMGROWTH!#REF! -> #REF! | C143: =TEAMGROWTH!#REF! -> #REF! | D143: =TEAMGROWTH!#REF! -> #REF! | E143: =TEAMGROWTH!#REF! -> #REF! | F143: =TEAMGROWTH!#REF! -> #REF! | G143: =TEAMGROWTH!#REF! -> #REF! | H143: =TEAMGROWTH!#REF! -> #REF! | ... M143: =TEAMGROWTH!#REF! -> #REF!
A144: =TEAMGROWTH!#REF! -> #REF! | B144: =TEAMGROWTH!#REF! -> #REF! | C144: =TEAMGROWTH!#REF! -> #REF! | D144: =TEAMGROWTH!#REF! -> #REF! | E144: =TEAMGROWTH!#REF! -> #REF! | F144: =TEAMGROWTH!#REF! -> #REF! | G144: =TEAMGROWTH!#REF! -> #REF! | H144: =TEAMGROWTH!#REF! -> #REF! | ... M144: =TEAMGROWTH!#REF! -> #REF!
A145: =TEAMGROWTH!#REF! -> #REF! | B145: =TEAMGROWTH!#REF! -> #REF! | C145: =TEAMGROWTH!#REF! -> #REF! | D145: =TEAMGROWTH!#REF! -> #REF! | E145: =TEAMGROWTH!#REF! -> #REF! | F145: =TEAMGROWTH!#REF! -> #REF! | G145: =TEAMGROWTH!#REF! -> #REF! | H145: =TEAMGROWTH!#REF! -> #REF! | ... M145: =TEAMGROWTH!#REF! -> #REF!
A146: =TEAMGROWTH!#REF! -> #REF! | B146: =TEAMGROWTH!#REF! -> #REF! | C146: =TEAMGROWTH!#REF! -> #REF! | D146: =TEAMGROWTH!#REF! -> #REF! | E146: =TEAMGROWTH!#REF! -> #REF! | F146: =TEAMGROWTH!#REF! -> #REF! | G146: =TEAMGROWTH!#REF! -> #REF! | H146: =TEAMGROWTH!#REF! -> #REF! | ... M146: =TEAMGROWTH!#REF! -> #REF!
A147: =TEAMGROWTH!#REF! -> #REF! | B147: =TEAMGROWTH!#REF! -> #REF! | C147: =TEAMGROWTH!#REF! -> #REF! | D147: =TEAMGROWTH!#REF! -> #REF! | E147: =TEAMGROWTH!#REF! -> #REF! | F147: =TEAMGROWTH!#REF! -> #REF! | G147: =TEAMGROWTH!#REF! -> #REF! | H147: =TEAMGROWTH!#REF! -> #REF! | ... M147: =TEAMGROWTH!#REF! -> #REF!
A148: =TEAMGROWTH!#REF! -> #REF! | B148: =TEAMGROWTH!#REF! -> #REF! | C148: =TEAMGROWTH!#REF! -> #REF! | D148: =TEAMGROWTH!#REF! -> #REF! | E148: =TEAMGROWTH!#REF! -> #REF! | F148: =TEAMGROWTH!#REF! -> #REF! | G148: =TEAMGROWTH!#REF! -> #REF! | H148: =TEAMGROWTH!#REF! -> #REF! | ... M148: =TEAMGROWTH!#REF! -> #REF!
A149: =TEAMGROWTH!#REF! -> #REF! | B149: =TEAMGROWTH!#REF! -> #REF! | C149: =TEAMGROWTH!#REF! -> #REF! | D149: =TEAMGROWTH!#REF! -> #REF! | E149: =TEAMGROWTH!#REF! -> #REF! | F149: =TEAMGROWTH!#REF! -> #REF! | G149: =TEAMGROWTH!#REF! -> #REF! | H149: =TEAMGROWTH!#REF! -> #REF! | ... M149: =TEAMGROWTH!#REF! -> #REF!
A150: =TEAMGROWTH!#REF! -> #REF! | B150: =TEAMGROWTH!#REF! -> #REF! | C150: =TEAMGROWTH!#REF! -> #REF! | D150: =TEAMGROWTH!#REF! -> #REF! | E150: =TEAMGROWTH!#REF! -> #REF! | F150: =TEAMGROWTH!#REF! -> #REF! | G150: =TEAMGROWTH!#REF! -> #REF! | H150: =TEAMGROWTH!#REF! -> #REF! | ... M150: =TEAMGROWTH!#REF! -> #REF!
A151: =TEAMGROWTH!#REF! -> #REF! | B151: =TEAMGROWTH!#REF! -> #REF! | C151: =TEAMGROWTH!#REF! -> #REF! | D151: =TEAMGROWTH!#REF! -> #REF! | E151: =TEAMGROWTH!#REF! -> #REF! | F151: =TEAMGROWTH!#REF! -> #REF! | G151: =TEAMGROWTH!#REF! -> #REF! | H151: =TEAMGROWTH!#REF! -> #REF! | ... M151: =TEAMGROWTH!#REF! -> #REF!
A152: =TEAMGROWTH!#REF! -> #REF! | B152: =TEAMGROWTH!#REF! -> #REF! | C152: =TEAMGROWTH!#REF! -> #REF! | D152: =TEAMGROWTH!#REF! -> #REF! | E152: =TEAMGROWTH!#REF! -> #REF! | F152: =TEAMGROWTH!#REF! -> #REF! | G152: =TEAMGROWTH!#REF! -> #REF! | H152: =TEAMGROWTH!#REF! -> #REF! | ... M152: =TEAMGROWTH!#REF! -> #REF!
A154: Effective Techs
B155: ='2023 Forecast Totals'!D$3 -> Jan | C155: ='2023 Forecast Totals'!E$3 -> Feb | D155: ='2023 Forecast Totals'!F$3 -> Mar | E155: ='2023 Forecast Totals'!G$3 -> Apr | F155: ='2023 Forecast Totals'!H$3 -> May | G155: ='2023 Forecast Totals'!I$3 -> Jun | H155: ='2023 Forecast Totals'!J$3 -> Jul | I155: ='2023 Forecast Totals'!K$3 -> Aug | ... M155: ='2023 Forecast Totals'!O$3 -> Dec | N155: ='2023 Forecast Totals'!Q$3 -> Jan | O155: ='2023 Forecast Totals'!R$3 -> Feb | P155: ='2023 Forecast Totals'!S$3 -> Mar | Q155: ='2023 Forecast Totals'!T$3 -> Apr | R155: ='2023 Forecast Totals'!U$3 -> May | S155: ='2023 Forecast Totals'!V$3 -> Jun | T155: ='2023 Forecast Totals'!W$3 -> Jul | U155: ='2023 Forecast Totals'!X$3 -> Aug | ... X155: ='2023 Forecast Totals'!AA$3 -> Nov | Y155: Dec | Z155: ='2023 Forecast Totals'!AD$3 -> Jan | AA155: ='2023 Forecast Totals'!AE$3 -> Feb | AB155: ='2023 Forecast Totals'!AF$3 -> Mar | AC155: ='2023 Forecast Totals'!AG$3 -> Apr | AD155: ='2023 Forecast Totals'!AH$3 -> May | AE155: ='2023 Forecast Totals'!AI$3 -> Jun | AF155: ='2023 Forecast Totals'!AJ$3 -> Jul | AG155: ='2023 Forecast Totals'!AK$3 -> Aug | ... AK155: ='2023 Forecast Totals'!AO$3 -> Dec
A156: ='2023 Forecast Totals'!A43 -> Effective Techs | B156: ='2023 Forecast Totals'!D43 -> 20.8 | C156: ='2023 Forecast Totals'!E43 -> 20.8 | D156: ='2023 Forecast Totals'!F43 -> 20.8 | E156: ='2023 Forecast Totals'!G43 -> 20.8 | F156: ='2023 Forecast Totals'!H43 -> 20.8 | G156: ='2023 Forecast Totals'!I43 -> 20.8 | H156: ='2023 Forecast Totals'!J43 -> 20.8 | I156: ='2023 Forecast Totals'!K43 -> 20.8 | ... M156: ='2023 Forecast Totals'!O43 -> 20.8 | N156: ='2023 Forecast Totals'!Q43 -> 24 | O156: ='2023 Forecast Totals'!R43 -> 28.8 | P156: ='2023 Forecast Totals'!S43 -> 28.8 | Q156: ='2023 Forecast Totals'!T43 -> 28.8 | R156: ='2023 Forecast Totals'!U43 -> 28.8 | S156: ='2023 Forecast Totals'!V43 -> 28.8 | T156: ='2023 Forecast Totals'!W43 -> 28.8 | U156: ='2023 Forecast Totals'!X43 -> 24 | ... Y156: ='2023 Forecast Totals'!AB43 -> 24 | Z156: ='2023 Forecast Totals'!AD43 -> 24 | AA156: ='2023 Forecast Totals'!AE43 -> 24 | AB156: ='2023 Forecast Totals'!AF43 -> 24 | AC156: ='2023 Forecast Totals'!AG43 -> 24 | AD156: ='2023 Forecast Totals'!AH43 -> 24 | AE156: ='2023 Forecast Totals'!AI43 -> 24 | AF156: ='2023 Forecast Totals'!AJ43 -> 24 | AG156: ='2023 Forecast Totals'!AK43 -> 24 | ... AK156: ='2023 Forecast Totals'!AO43 -> 24
A157: ='Man Hours & Costs'!A4 -> BDU Actual Techs | B157: ='Man Hours & Costs'!C4 -> 26 | C157: ='Man Hours & Costs'!D4 -> 26 | D157: ='Man Hours & Costs'!E4 -> 26 | E157: ='Man Hours & Costs'!F4 -> 26 | F157: ='Man Hours & Costs'!G4 -> 26 | G157: ='Man Hours & Costs'!H4 -> 26 | H157: ='Man Hours & Costs'!I4 -> 26 | I157: ='Man Hours & Costs'!J4 -> 26 | ... M157: ='Man Hours & Costs'!N4 -> 26 | N157: ='Man Hours & Costs'!P4 -> 30 | O157: ='Man Hours & Costs'!Q4 -> 36 | P157: ='Man Hours & Costs'!R4 -> 36 | Q157: ='Man Hours & Costs'!S4 -> 36 | R157: ='Man Hours & Costs'!T4 -> 36 | S157: ='Man Hours & Costs'!U4 -> 36 | T157: ='Man Hours & Costs'!V4 -> 36 | U157: ='Man Hours & Costs'!W4 -> 30 | ... Y157: ='Man Hours & Costs'!AA4 -> 30 | Z157: ='Man Hours & Costs'!AC4 -> 30 | AA157: ='Man Hours & Costs'!AD4 -> 30 | AB157: ='Man Hours & Costs'!AE4 -> 30 | AC157: ='Man Hours & Costs'!AF4 -> 30 | AD157: ='Man Hours & Costs'!AG4 -> 30 | AE157: ='Man Hours & Costs'!AH4 -> 30 | AF157: ='Man Hours & Costs'!AI4 -> 30 | AG157: ='Man Hours & Costs'!AJ4 -> 30 | ... AK157: ='Man Hours & Costs'!AN4 -> 30
A159: Calibrated MH
B160: ='2023 Forecast Totals'!D$3 -> Jan | C160: ='2023 Forecast Totals'!E$3 -> Feb | D160: ='2023 Forecast Totals'!F$3 -> Mar | E160: ='2023 Forecast Totals'!G$3 -> Apr | F160: ='2023 Forecast Totals'!H$3 -> May | G160: ='2023 Forecast Totals'!I$3 -> Jun | H160: ='2023 Forecast Totals'!J$3 -> Jul | I160: ='2023 Forecast Totals'!K$3 -> Aug | ... M160: ='2023 Forecast Totals'!O$3 -> Dec | N160: ='2023 Forecast Totals'!Q$3 -> Jan | O160: ='2023 Forecast Totals'!R$3 -> Feb | P160: ='2023 Forecast Totals'!S$3 -> Mar | Q160: ='2023 Forecast Totals'!T$3 -> Apr | R160: ='2023 Forecast Totals'!U$3 -> May | S160: ='2023 Forecast Totals'!V$3 -> Jun | T160: ='2023 Forecast Totals'!W$3 -> Jul | U160: ='2023 Forecast Totals'!X$3 -> Aug | ... X160: ='2023 Forecast Totals'!AA$3 -> Nov | Y160: Dec | Z160: ='2023 Forecast Totals'!AD$3 -> Jan | AA160: ='2023 Forecast Totals'!AE$3 -> Feb | AB160: ='2023 Forecast Totals'!AF$3 -> Mar | AC160: ='2023 Forecast Totals'!AG$3 -> Apr | AD160: ='2023 Forecast Totals'!AH$3 -> May | AE160: ='2023 Forecast Totals'!AI$3 -> Jun | AF160: ='2023 Forecast Totals'!AJ$3 -> Jul | AG160: ='2023 Forecast Totals'!AK$3 -> Aug | ... AK160: ='2023 Forecast Totals'!AO$3 -> Dec
A161: ='2023 Forecast Totals'!A41 -> Total Revenue | B161: ='2023 Forecast Totals'!D29 -> 3071 | C161: ='2023 Forecast Totals'!E29 -> 3106.5 | D161: ='2023 Forecast Totals'!F29 -> 3142 | E161: ='2023 Forecast Totals'!G29 -> 3177.5 | F161: ='2023 Forecast Totals'!H29 -> 3177.5 | G161: ='2023 Forecast Totals'!I29 -> 3177.5 | H161: ='2023 Forecast Totals'!J29 -> 3213 | I161: ='2023 Forecast Totals'!K29 -> 3213 | ... M161: ='2023 Forecast Totals'!O29 -> 3248.5 | N161: ='2023 Forecast Totals'!Q29 -> 3248.5 | O161: ='2023 Forecast Totals'!R29 -> 3248.5 | P161: ='2023 Forecast Totals'!S29 -> 3248.5 | Q161: ='2023 Forecast Totals'!T29 -> 3248.5 | R161: ='2023 Forecast Totals'!U29 -> 3248.5 | S161: ='2023 Forecast Totals'!V29 -> 248.5 | T161: ='2023 Forecast Totals'!W29 -> 3248.5 | U161: ='2023 Forecast Totals'!X29 -> 3248.5 | ... Y161: ='2023 Forecast Totals'!AB29 -> 248.5 | Z161: ='2023 Forecast Totals'!AD29 -> 3248.5 | AA161: ='2023 Forecast Totals'!AE29 -> 3248.5 | AB161: ='2023 Forecast Totals'!AF29 -> 3248.5 | AC161: ='2023 Forecast Totals'!AG29 -> 3248.5 | AD161: ='2023 Forecast Totals'!AH29 -> 3248.5 | AE161: ='2023 Forecast Totals'!AI29 -> 3248.5 | AF161: ='2023 Forecast Totals'!AJ29 -> 3248.5 | AG161: ='2023 Forecast Totals'!AK29 -> 3248.5 | ... AK161: ='2023 Forecast Totals'!AO29 -> 3248.5
A162: ='2023 Forecast Totals'!A44 -> Billable hours free | B162: ='2023 Forecast Totals'!D44 -> 3260.192 | C162: ='2023 Forecast Totals'!E44 -> 3095.04 | D162: ='2023 Forecast Totals'!F44 -> 3590.496 | E162: ='2023 Forecast Totals'!G44 -> 3095.04 | F162: ='2023 Forecast Totals'!H44 -> 3425.344 | G162: ='2023 Forecast Totals'!I44 -> 3425.344 | H162: ='2023 Forecast Totals'!J44 -> 3095.04 | I162: ='2023 Forecast Totals'!K44 -> 3590.496 | ... M162: ='2023 Forecast Totals'!O44 -> 2434.432 | N162: ='2023 Forecast Totals'!Q44 -> 3761.76 | O162: ='2023 Forecast Totals'!R44 -> 4285.44 | P162: ='2023 Forecast Totals'!S44 -> 4971.456 | Q162: ='2023 Forecast Totals'!T44 -> 4285.44 | R162: ='2023 Forecast Totals'!U44 -> 4742.784 | S162: ='2023 Forecast Totals'!V44 -> 4742.784 | T162: ='2023 Forecast Totals'!W44 -> 4285.44 | U162: ='2023 Forecast Totals'!X44 -> 4142.88 | ... Y162: ='2023 Forecast Totals'!AB44 -> 2808.96 | Z162: ='2023 Forecast Totals'!AD29 -> 3248.5 | AA162: ='2023 Forecast Totals'!AE44 -> 3571.2 | AB162: ='2023 Forecast Totals'!AF44 -> 4142.88 | AC162: ='2023 Forecast Totals'!AG44 -> 3571.2 | AD162: ='2023 Forecast Totals'!AH44 -> 3952.32 | AE162: ='2023 Forecast Totals'!AI44 -> 3952.32 | AF162: ='2023 Forecast Totals'!AJ44 -> 3571.2 | AG162: ='2023 Forecast Totals'!AK44 -> 4142.88 | AH162: ='2023 Forecast Totals'!AL44 -> 3571.2 | ... AK162: ='2023 Forecast Totals'!AO44 -> 2808.96
A163: Buffer | B163: =B162+(B162*(-1*Controls!$E$16)) -> 2934.1728 | C163: =C162+(C162*(-1*Controls!$E$16)) -> 2785.536 | D163: =D162+(D162*(-1*Controls!$E$16)) -> 3231.4464 | E163: =E162+(E162*(-1*Controls!$E$16)) -> 2785.536 | F163: =F162+(F162*(-1*Controls!$E$16)) -> 3082.8096 | G163: =G162+(G162*(-1*Controls!$E$16)) -> 3082.8096 | H163: =H162+(H162*(-1*Controls!$E$16)) -> 2785.536 | I163: =I162+(I162*(-1*Controls!$E$16)) -> 3231.4464 | ... AK163: =AK162+(AK162*(-1*Controls!$E$16)) -> 2528.064
A165: Cash Flow
B166: ='2023 Forecast Totals'!D$3 -> Jan | C166: ='2023 Forecast Totals'!E$3 -> Feb | D166: ='2023 Forecast Totals'!F$3 -> Mar | E166: ='2023 Forecast Totals'!G$3 -> Apr | F166: ='2023 Forecast Totals'!H$3 -> May | G166: ='2023 Forecast Totals'!I$3 -> Jun | H166: ='2023 Forecast Totals'!J$3 -> Jul | I166: ='2023 Forecast Totals'!K$3 -> Aug | ... M166: ='2023 Forecast Totals'!O$3 -> Dec | N166: ='2023 Forecast Totals'!Q$3 -> Jan | O166: ='2023 Forecast Totals'!R$3 -> Feb | P166: ='2023 Forecast Totals'!S$3 -> Mar | Q166: ='2023 Forecast Totals'!T$3 -> Apr | R166: ='2023 Forecast Totals'!U$3 -> May | S166: ='2023 Forecast Totals'!V$3 -> Jun | T166: ='2023 Forecast Totals'!W$3 -> Jul | U166: ='2023 Forecast Totals'!X$3 -> Aug | ... Y166: ='2023 Forecast Totals'!AB$3 -> Dec | Z166: ='2023 Forecast Totals'!AD$3 -> Jan | AA166: ='2023 Forecast Totals'!AE$3 -> Feb | AB166: ='2023 Forecast Totals'!AF$3 -> Mar | AC166: ='2023 Forecast Totals'!AG$3 -> Apr | AD166: ='2023 Forecast Totals'!AH$3 -> May | AE166: ='2023 Forecast Totals'!AI$3 -> Jun | AF166: ='2023 Forecast Totals'!AJ$3 -> Jul | AG166: ='2023 Forecast Totals'!AK$3 -> Aug | ... AK166: ='2023 Forecast Totals'!AO$3 -> Dec
A167: Total costs | B167: ='2023 Forecast Totals'!D61*-1 -> 246486.24 | C167: ='2023 Forecast Totals'!E61*-1 -> 234748.8 | D167: ='2023 Forecast Totals'!F61*-1 -> 269961.12 | E167: ='2023 Forecast Totals'!G61*-1 -> 234748.8 | F167: ='2023 Forecast Totals'!H61*-1 -> 258223.68 | G167: ='2023 Forecast Totals'!I61*-1 -> 258223.68 | H167: ='2023 Forecast Totals'!J61*-1 -> 234748.8 | I167: ='2023 Forecast Totals'!K61*-1 -> 269961.12 | ... M167: ='2023 Forecast Totals'!O61*-1 -> 187799.04 | N167: ='2023 Forecast Totals'!Q61*-1 -> 284407.2 | O167: ='2023 Forecast Totals'!R61*-1 -> 325036.8 | P167: ='2023 Forecast Totals'!S61*-1 -> 373792.32 | Q167: ='2023 Forecast Totals'!T61*-1 -> 325036.8 | R167: ='2023 Forecast Totals'!U61*-1 -> 357540.48 | S167: ='2023 Forecast Totals'!V61*-1 -> 357540.48 | T167: ='2023 Forecast Totals'!W61*-1 -> 325036.8 | U167: ='2023 Forecast Totals'!X61*-1 -> 311493.6 | ... Y167: ='2023 Forecast Totals'!AB61*-1 -> 216691.2 | Z167: ='2023 Forecast Totals'!AD61*-1 -> 284407.2 | AA167: ='2023 Forecast Totals'!AE61*-1 -> 270864 | AB167: ='2023 Forecast Totals'!AF61*-1 -> 311493.6 | AC167: ='2023 Forecast Totals'!AG61*-1 -> 270864 | AD167: ='2023 Forecast Totals'!AH61*-1 -> 297950.4 | AE167: ='2023 Forecast Totals'!AI61*-1 -> 297950.4 | AF167: ='2023 Forecast Totals'!AJ61*-1 -> 270864 | AG167: ='2023 Forecast Totals'!AK61*-1 -> 311493.6 | ... AK167: ='2023 Forecast Totals'!AO61*-1 -> 216691.2
A168: Total income | B168: ='2023 Forecast Totals'!D63 -> 60613.76 | C168: ='2023 Forecast Totals'!E63 -> 75901.2 | D168: ='2023 Forecast Totals'!F63 -> 44238.88 | E168: ='2023 Forecast Totals'!G63 -> 83001.2 | F168: ='2023 Forecast Totals'!H63 -> 59526.32 | G168: ='2023 Forecast Totals'!I63 -> 59526.32 | H168: ='2023 Forecast Totals'!J63 -> 86551.2 | I168: ='2023 Forecast Totals'!K63 -> 51338.88 | ... M168: ='2023 Forecast Totals'!O63 -> 137050.96 | N168: ='2023 Forecast Totals'!Q63 -> 40442.8 | O168: ='2023 Forecast Totals'!R63 -> -186.8 | P168: ='2023 Forecast Totals'!S63 -> -48942.32 | Q168: ='2023 Forecast Totals'!T63 -> -186.8 | R168: ='2023 Forecast Totals'!U63 -> -32690.48 | S168: ='2023 Forecast Totals'!V63 -> -332690.48 | T168: ='2023 Forecast Totals'!W63 -> -186.8 | U168: ='2023 Forecast Totals'!X63 -> 13356.4 | ... Y168: ='2023 Forecast Totals'!AB63 -> -191841.2 | Z168: ='2023 Forecast Totals'!AD63 -> 40442.8 | AA168: ='2023 Forecast Totals'!AE63 -> 53986 | AB168: ='2023 Forecast Totals'!AF63 -> 13356.4 | AC168: ='2023 Forecast Totals'!AG63 -> 53986 | AD168: ='2023 Forecast Totals'!AH63 -> 26899.6 | AE168: ='2023 Forecast Totals'!AI63 -> 26899.6 | AF168: ='2023 Forecast Totals'!AJ63 -> 53986 | AG168: ='2023 Forecast Totals'!AK63 -> 13356.4 | ... AK168: ='2023 Forecast Totals'!AO63 -> 108158.8
A169: Total cash flow | B169: ='2023 Forecast Totals'!D65 -> 60613.76 | C169: ='2023 Forecast Totals'!E65 -> 75901.2 | D169: ='2023 Forecast Totals'!F65 -> 44238.88 | E169: ='2023 Forecast Totals'!G65 -> 83001.2 | F169: ='2023 Forecast Totals'!H65 -> 59526.32 | G169: ='2023 Forecast Totals'!I65 -> 59526.32 | H169: ='2023 Forecast Totals'!J65 -> 86551.2 | I169: ='2023 Forecast Totals'!K65 -> 51338.88 | ... M169: ='2023 Forecast Totals'!O65 -> 137050.96 | N169: ='2023 Forecast Totals'!Q65 -> 40442.8 | O169: ='2023 Forecast Totals'!R65 -> -186.8 | P169: ='2023 Forecast Totals'!S65 -> -48942.32 | Q169: ='2023 Forecast Totals'!T65 -> -186.8 | R169: ='2023 Forecast Totals'!U65 -> -32690.48 | S169: ='2023 Forecast Totals'!V65 -> -332690.48 | T169: ='2023 Forecast Totals'!W65 -> -186.8 | U169: ='2023 Forecast Totals'!X65 -> 13356.4 | ... Y169: ='2023 Forecast Totals'!AB65 -> -191841.2 | Z169: ='2023 Forecast Totals'!AD65 -> 40442.8 | AA169: ='2023 Forecast Totals'!AE65 -> 53986 | AB169: ='2023 Forecast Totals'!AF65 -> 13356.4 | AC169: ='2023 Forecast Totals'!AG65 -> 53986 | AD169: ='2023 Forecast Totals'!AH65 -> 26899.6 | AE169: ='2023 Forecast Totals'!AI65 -> 26899.6 | AF169: ='2023 Forecast Totals'!AJ65 -> 53986 | AG169: ='2023 Forecast Totals'!AK65 -> 13356.4 | ... AK169: ='2023 Forecast Totals'!AO65 -> 108158.8
A170: Percentage | B170: =(B168/B167)-1 -> -0.75408867 | C170: =(C168/C167)-1 -> -0.67667055 | D170: =(D168/D167)-1 -> -0.8361287 | E170: =(E168/E167)-1 -> -0.64642546 | F170: =(F168/F167)-1 -> -0.76947769 | G170: =(G168/G167)-1 -> -0.76947769 | H170: =(H168/H167)-1 -> -0.63130291 | I170: =(I168/I167)-1 -> -0.80982862 | ... AK170: =(AK168/AK167)-1 -> -0.50086206

Sheet Controls
C2: Billable time worksheet
D3: Mins | E3: Hours
C4: Time in day | D4: =E4*60 -> 480 | E4: 8
C5: Daily Breaks | D5: 30 | E5: =D5/60 -> 0.5
C6: Daily Lunches | E6: =D6/60 -> 0
C7: Daily Clean up | D7: 15 | E7: =D7/60 -> 0.25
C8: Daily Meetings | D8: 9 | E8: =D8/60 -> 0.15
C9: Total reduction | D9: =SUM(D5:D8)*-1 -> -54 | E9: =D9/60 -> -0.9
C11: Daily billiable | D11: ='Man Hours & Costs'!S4+D9 -> -18 | E11: =D11/60 -> -0.3
B12: Total time available for productive work | C12: Total billable time in day | D12: =D4+D11 -> 462 | E12: =D12/60 -> 7.7
C13: Total billable time with OT | D13: =D12+(D12*E15) -> 475.86 | E13: =D13/60 -> 7.931
C15: Overtime Assumption | E15: 0.03
C16: Work Buffer | E16: 0.1
C17: Total number of technicans BJC | D17: =COUNTA(TEAMGROWTH!D27:D43) -> 8
C18: Total number of tech SLC | D18: =COUNTA(TEAMGROWTH!D58:D63) -> 1
C19: Avalible time for billing | D19: Start billiable amount NEW TECH | E19: Change needed | F19: Months to fully billable | G19: Increase % per month | H19: Months to Average work load
C20: High | D20: 0.25 | E20: =D20-1 -> -0.75 | F20: 6 | G20: =(E20/F20)*-1*(1) -> 0.125 | H20: 9
C21: Medium | D21: 0.25 | E21: =D21-1 -> -0.75 | F21: 9 | G21: =(E21/F21)*-1 -> 0.083333333 | H21: 10.5
C22: Low | D22: 0.1 | E22: =D22-1 -> -0.9 | F22: 12 | G22: =(E22/F22)*-1 -> 0.075 | H22: 18
C23: Helper not on path to A&P - Extra Low | D23: 0 | E23: =D23-1 -> -1 | F23: 24 | G23: =(E23/F23)*-1 -> 0.041666667 | H23: 36
C24: Position reducitons | D24: Of total | E24: Mins | F24: Hours
C25: AP | D25: 0 | E25: =TEAMGROWTH!C23*D25 -> 0 | F25: =E25/60 -> 0
C26: CC - Crew Chief | D26: 0.7 | E26: =$D$13*D26 -> 333.102 | F26: =E26/60 -> 5.5517
C27: AV - Avionics Tech | D27: 0 | E27: =$D$13*D27 -> 0 | F27: =E27/60 -> 0
C28: AV CC - Avonics Crew Chief | D28: 0.6 | E28: =$D$13*D28 -> 285.516 | F28: =E28/60 -> 4.7586
C29: SF- Shop Foreman | D29: 0.5 | E29: =$D$13*D29 -> 237.93 | F29: =E29/60 -> 3.9655
C30: DOM | D30: 1 | E30: =$D$13*D30 -> 475.86 | F30: =E30/60 -> 7.931
C32: PTO
D34: January | E34: Febuary | F34: March | G34: April | H34: May | I34: June | J34: July | K34: August | L34: September | M34: October | N34: November | O34: December
C35: CO AV | D35: 8 | E35: 0 | F35: 0 | G35: 10.66 | H35: 0 | I35: 0 | J35: 5.33 | K35: 2.66 | L35: 2.66 | M35: 0 | N35: 8
C36: CA AV | D36: 26.66 | E36: 0 | F36: 21.3 | G36: 16 | H36: 0 | I36: 3.24 | J36: 24 | K36: 2.66 | L36: 8 | M36: 5.33 | N36: 12
C37: CO MX | D37: 11.59 | E37: 4.251 | F37: 4.91 | G37: 7.4 | H37: 12.42 | I37: 16.34 | J37: 4 | K37: 0 | L37: 15.2 | M37: 8.3 | N37: 3.8
C38: CA MX | D38: 10.66 | E38: 15.38 | F38: 5.38 | G38: 5.8 | H38: 4.5 | I38: 8 | J38: 16.69 | K38: 1 | L38: 6 | M38: 3.33 | N38: 31
C39: Total | D39: 14.2275 | E39: 4.90775 | F39: 7.8975 | G39: 9.965 | H39: 4.23 | I39: 6.895 | J39: 12.505 | K39: 1.58 | L39: 7.965 | M39: 4.24 | N39: 13.7 | O39: 0
Q40: Average hours per month per person excluding december | R40: 8.01025
Q41: Number of technicians | R41: 18
Q42: Total hours lost per month | R42: 144.1845
C43: Hangar Capacity | Q43: Total hours in 4 weeks (BJC 18 techs) | R43: 2880
Q44: % LOSS | R44: 0.050064063
C45: Monthly turn rate / bay 6 day turn | D45: 4 | Q45: Total person loss | R45: 0.9
C46: Bays | D46: 8
C47: Total WO slots | D47: =D45*D46 -> 32
C49: Total compensation cashflow non-executive positions | D49: Hourly rates | E49: 2080
C51: Sam Perez Service Manager (AP/IA) | D51: 54 | E51: =D51*$E$49 -> 112320
C52: Joe Vigil AP/AV | D52: 54 | E52: =D52*$E$49 -> 112320
C53: X Mech 1, 1-3YR AP | D53: 54 | E53: =D53*$E$49 -> 112320
C54: X Mech 2, 1-3YR Entry AP | D54: 54 | E54: =D54*$E$49 -> 112320
C55: X Mech 3, Entry AP | D55: 54 | E55: =D55*$E$49 -> 112320
C56: X Mech 4, Entry AP | D56: 54 | E56: =D56*$E$49 -> 112320
C57: Detailer and line support | D57: 54 | E57: =D57*$E$49 -> 112320
E58: =SUM(E50:E57) -> 786240
C59: Average | D59: =AVERAGE(D50:D57)*-1 -> -54 | E59: =AVERAGE(E50:E57) -> 112320
C61: Executive compensation | E61: -11666
C62: Sam Sandifer DOM | E62: -5520
C63: Parts clerk | D63: -29 | E63: =D63*E49 -> -60320
C66: Piston shop rate / HR | D66: 120
C67: Turbine shop rate / HR | D67: 155
C70: Tool allowance | D70: =D72 -> -125
C71: Total compensation | D71: -1500
C72: Monthly breakdown | D72: =D71/12 -> -125

Sheet Man Hours & Costs
A2: Paid Hours
C3: Jan | D3: Feb | E3: Mar | F3: Apr | G3: May | H3: Jun | I3: Jul | J3: Aug | K3: Sep | L3: Oct | M3: Nov | N3: Dec | O3: 2024 Totals | P3: Jan | Q3: Feb | R3: Mar | S3: Apr | T3: May | U3: Jun | V3: Jul | W3: Aug | X3: Sep | Y3: Oct | Z3: Nov | AA3: Dec | AB3: 2025 Totals | AC3: Jan | AD3: Feb | AE3: Mar | AF3: Apr | AG3: May | AH3: Jun | AI3: Jul | AJ3: Aug | AK3: Sep | AL3: Oct | AM3: Nov | AN3: Dec | AO3: 2026 Totals
A4: BDU Actual Techs | C4: ='2023 Forecast Totals'!D2 -> 26 | D4: ='2023 Forecast Totals'!E2 -> 26 | E4: ='2023 Forecast Totals'!F2 -> 26 | F4: ='2023 Forecast Totals'!G2 -> 26 | G4: ='2023 Forecast Totals'!H2 -> 26 | H4: ='2023 Forecast Totals'!I2 -> 26 | I4: ='2023 Forecast Totals'!J2 -> 26 | J4: ='2023 Forecast Totals'!K2 -> 26 | ... AO4: ='2023 Forecast Totals'!AP2 -> 30
A5: MH Hours paid per day | C5: 8 | D5: 8 | E5: 8 | F5: 8 | G5: 8 | H5: 8 | I5: 8 | J5: 8 | K5: 8 | L5: 8 | M5: 8 | N5: 8 | P5: 8 | Q5: 8 | R5: 8 | S5: 8 | T5: 8 | U5: 8 | V5: 8 | W5: 8 | X5: 8 | Y5: 8 | Z5: 8 | AA5: 8 | AC5: 8 | AD5: 8 | AE5: 8 | AF5: 8 | AG5: 8 | AH5: 8 | AI5: 8 | AJ5: 8 | AK5: 8 | AL5: 8 | AM5: 8 | AN5: 8
A6: Working days in month (minus holiday) | C6: 21 | D6: 20 | E6: 23 | F6: 20 | G6: 22 | H6: 22 | I6: 20 | J6: 23 | K6: 20 | L6: 22 | M6: 20 | N6: 16 | O6: =SUM(C6:N6) -> 249 | P6: 21 | Q6: 20 | R6: 23 | S6: 20 | T6: 22 | U6: 22 | V6: 20 | W6: 23 | X6: 20 | Y6: 22 | Z6: 20 | AA6: 16 | AB6: =SUM(P6:AA6) -> 249 | AC6: 21 | AD6: 20 | AE6: 23 | AF6: 20 | AG6: 22 | AH6: 22 | AI6: 20 | AJ6: 23 | AK6: 20 | AL6: 22 | AM6: 20 | AN6: 16 | AO6: =SUM(AC6:AN6) -> 249
A7: Paid holidays | B7: =B24 -> -54 | C7: 1 | G7: 1 | I7: 1 | M7: 1 | N7: 1 | P7: 1 | T7: 1 | V7: 1 | Z7: 1 | AA7: 1 | AC7: 1 | AG7: 1 | AI7: 1 | AM7: 1 | AN7: 1
A8: Total paid MH per day | C8: =C4*C5 -> 208 | D8: =D4*D5 -> 208 | E8: =E4*E5 -> 208 | F8: =F4*F5 -> 208 | G8: =G4*G5 -> 208 | H8: =H4*H5 -> 208 | I8: =I4*I5 -> 208 | J8: =J4*J5 -> 208 | ... N8: =N4*N5 -> 208 | P8: =P4*P5 -> 240 | Q8: =Q4*Q5 -> 288 | R8: =R4*R5 -> 288 | S8: =S4*S5 -> 288 | T8: =T4*T5 -> 288 | U8: =U4*U5 -> 288 | V8: =V4*V5 -> 288 | W8: =W4*W5 -> 240 | ... AA8: =AA4*AA5 -> 240 | AC8: =AC4*AC5 -> 240 | AD8: =AD4*AD5 -> 240 | AE8: =AE4*AE5 -> 240 | AF8: =AF4*AF5 -> 240 | AG8: =AG4*AG5 -> 240 | AH8: =AH4*AH5 -> 240 | AI8: =AI4*AI5 -> 240 | AJ8: =AJ4*AJ5 -> 240 | ... AN8: =AN4*AN5 -> 240
A9: Average Montly MH | C9: =C6*C8 -> 4368 | D9: =D6*D8 -> 4160 | E9: =E6*E8 -> 4784 | F9: =F6*F8 -> 4160 | G9: =G6*G8 -> 4576 | H9: =H6*H8 -> 4576 | I9: =I6*I8 -> 4160 | J9: =J6*J8 -> 4784 | ... N9: =N6*N8 -> 3328 | O9: =SUM(C9:N9) -> 51792 | P9: =P6*P8 -> 5040 | Q9: =Q6*Q8 -> 5760 | R9: =R6*R8 -> 6624 | S9: =S6*S8 -> 5760 | T9: =T6*T8 -> 6336 | U9: =U6*U8 -> 6336 | V9: =V6*V8 -> 5760 | W9: =W6*W8 -> 5520 | ... AA9: =AA6*AA8 -> 3840 | AB9: =SUM(P9:AA9) -> 65856 | AC9: =AC6*AC8 -> 5040 | AD9: =AD6*AD8 -> 4800 | AE9: =AE6*AE8 -> 5520 | AF9: =AF6*AF8 -> 4800 | AG9: =AG6*AG8 -> 5280 | AH9: =AH6*AH8 -> 5280 | AI9: =AI6*AI8 -> 4800 | AJ9: =AJ6*AJ8 -> 5520 | ... AN9: =AN6*AN8 -> 3840 | AO9: =SUM(AC9:AN9) -> 59760
A10: OT Assumption: | B10: =Controls!E15 -> 0.03
A11: Daily OT hours | C11: =C8*$B$10 -> 6.24 | D11: =D8*$B$10 -> 6.24 | E11: =E8*$B$10 -> 6.24 | F11: =F8*$B$10 -> 6.24 | G11: =G8*$B$10 -> 6.24 | H11: =H8*$B$10 -> 6.24 | I11: =I8*$B$10 -> 6.24 | J11: =J8*$B$10 -> 6.24 | ... N11: =N8*$B$10 -> 6.24 | O11: =SUM(C11:N11) -> 74.88 | P11: =P8*$B$10 -> 7.2 | Q11: =Q8*$B$10 -> 8.64 | R11: =R8*$B$10 -> 8.64 | S11: =S8*$B$10 -> 8.64 | T11: =T8*$B$10 -> 8.64 | U11: =U8*$B$10 -> 8.64 | V11: =V8*$B$10 -> 8.64 | W11: =W8*$B$10 -> 7.2 | ... AA11: =AA8*$B$10 -> 7.2 | AB11: =SUM(P11:AA11) -> 95.04 | AC11: =AC8*$B$10 -> 7.2 | AD11: =AD8*$B$10 -> 7.2 | AE11: =AE8*$B$10 -> 7.2 | AF11: =AF8*$B$10 -> 7.2 | AG11: =AG8*$B$10 -> 7.2 | AH11: =AH8*$B$10 -> 7.2 | AI11: =AI8*$B$10 -> 7.2 | AJ11: =AJ8*$B$10 -> 7.2 | ... AN11: =AN8*$B$10 -> 7.2 | AO11: =SUM(AC11:AN11) -> 86.4
A12: Monthly OT MH hours | C12: =C11*C6 -> 131.04 | D12: =D11*D6 -> 124.8 | E12: =E11*E6 -> 143.52 | F12: =F11*F6 -> 124.8 | G12: =G11*G6 -> 137.28 | H12: =H11*H6 -> 137.28 | I12: =I11*I6 -> 124.8 | J12: =J11*J6 -> 143.52 | ... N12: =N11*N6 -> 99.84 | O12: =SUM(C12:N12) -> 1553.76 | P12: =P11*P6 -> 151.2 | Q12: =Q11*Q6 -> 172.8 | R12: =R11*R6 -> 198.72 | S12: =S11*S6 -> 172.8 | T12: =T11*T6 -> 190.08 | U12: =U11*U6 -> 190.08 | V12: =V11*V6 -> 172.8 | W12: =W11*W6 -> 165.6 | ... AA12: =AA11*AA6 -> 115.2 | AB12: =SUM(P12:AA12) -> 1975.68 | AC12: =AC11*AC6 -> 151.2 | AD12: =AD11*AD6 -> 144 | AE12: =AE11*AE6 -> 165.6 | AF12: =AF11*AF6 -> 144 | AG12: =AG11*AG6 -> 158.4 | AH12: =AH11*AH6 -> 158.4 | AI12: =AI11*AI6 -> 144 | AJ12: =AJ11*AJ6 -> 165.6 | ... AN12: =AN11*AN6 -> 115.2 | AO12: =SUM(AC12:AN12) -> 1792.8
A13: paid hrs per day | C13: =C11+C8 -> 214.24 | D13: =D11+D8 -> 214.24 | E13: =E11+E8 -> 214.24 | F13: =F11+F8 -> 214.24 | G13: =G11+G8 -> 214.24 | H13: =H11+H8 -> 214.24 | I13: =I11+I8 -> 214.24 | J13: =J11+J8 -> 214.24 | ... N13: =N11+N8 -> 214.24 | P13: =P11+P8 -> 247.2 | Q13: =Q11+Q8 -> 296.64 | R13: =R11+R8 -> 296.64 | S13: =S11+S8 -> 296.64 | T13: =T11+T8 -> 296.64 | U13: =U11+U8 -> 296.64 | V13: =V11+V8 -> 296.64 | W13: =W11+W8 -> 247.2 | ... AA13: =AA11+AA8 -> 247.2 | AC13: =AC11+AC8 -> 247.2 | AD13: =AD11+AD8 -> 247.2 | AE13: =AE11+AE8 -> 247.2 | AF13: =AF11+AF8 -> 247.2 | AG13: =AG11+AG8 -> 247.2 | AH13: =AH11+AH8 -> 247.2 | AI13: =AI11+AI8 -> 247.2 | AJ13: =AJ11+AJ8 -> 247.2 | ... AN13: =AN11+AN8 -> 247.2
A14: Total paid hours monthly | C14: =(C4*C5*C6)+C12 -> 4499.04 | D14: =(D4*D5*D6)+D12 -> 4284.8 | E14: =(E4*E5*E6)+E12 -> 4927.52 | F14: =(F4*F5*F6)+F12 -> 4284.8 | G14: =(G4*G5*G6)+G12 -> 4713.28 | H14: =(H4*H5*H6)+H12 -> 4713.28 | I14: =(I4*I5*I6)+I12 -> 4284.8 | J14: =(J4*J5*J6)+J12 -> 4927.52 | ... N14: =(N4*N5*N6)+N12 -> 3427.84 | O14: =SUM(C14:N14) -> 53345.76 | P14: =(P4*P5*P6)+P12 -> 5191.2 | Q14: =(Q4*Q5*Q6)+Q12 -> 5932.8 | R14: =(R4*R5*R6)+R12 -> 6822.72 | S14: =(S4*S5*S6)+S12 -> 5932.8 | T14: =(T4*T5*T6)+T12 -> 6526.08 | U14: =(U4*U5*U6)+U12 -> 6526.08 | V14: =(V4*V5*V6)+V12 -> 5932.8 | W14: =(W4*W5*W6)+W12 -> 5685.6 | ... AA14: =(AA4*AA5*AA6)+AA12 -> 3955.2 | AB14: =SUM(P14:AA14) -> 67831.68 | AC14: =(AC4*AC5*AC6)+AC12 -> 5191.2 | AD14: =(AD4*AD5*AD6)+AD12 -> 4944 | AE14: =(AE4*AE5*AE6)+AE12 -> 5685.6 | AF14: =(AF4*AF5*AF6)+AF12 -> 4944 | AG14: =(AG4*AG5*AG6)+AG12 -> 5438.4 | AH14: =(AH4*AH5*AH6)+AH12 -> 5438.4 | AI14: =(AI4*AI5*AI6)+AI12 -> 4944 | AJ14: =(AJ4*AJ5*AJ6)+AJ12 -> 5685.6 | ... AN14: =(AN4*AN5*AN6)+AN12 -> 3955.2 | AO14: =SUM(AC14:AN14) -> 61552.8
A15: Utilization Assumption:
A16: Total possible billable hours | C16: =(Controls!$E$12*C4*C6)+(C12) -> 4335.24 | D16: =(Controls!$E$12*D4*D6)+(D12) -> 4128.8 | E16: =(Controls!$E$12*E4*E6)+(E12) -> 4748.12 | F16: =(Controls!$E$12*F4*F6)+(F12) -> 4128.8 | G16: =(Controls!$E$12*G4*G6)+(G12) -> 4541.68 | H16: =(Controls!$E$12*H4*H6)+(H12) -> 4541.68 | I16: =(Controls!$E$12*I4*I6)+(I12) -> 4128.8 | J16: =(Controls!$E$12*J4*J6)+(J12) -> 4748.12 | ... N16: =(Controls!$E$12*N4*N6)+(N12) -> 3303.04 | O16: =SUM(C16:N16) -> 51403.56 | P16: =(Controls!$E$12*P4*P6)+(P12) -> 5002.2 | Q16: =(Controls!$E$12*Q4*Q6)+(Q12) -> 5716.8 | R16: =(Controls!$E$12*R4*R6)+(R12) -> 6574.32 | S16: =(Controls!$E$12*S4*S6)+(S12) -> 5716.8 | T16: =(Controls!$E$12*T4*T6)+(T12) -> 6288.48 | U16: =(Controls!$E$12*U4*U6)+(U12) -> 6288.48 | V16: =(Controls!$E$12*V4*V6)+(V12) -> 5716.8 | W16: =(Controls!$E$12*W4*W6)+(W12) -> 5478.6 | ... AA16: =(Controls!$E$12*AA4*AA6)+(AA12) -> 3811.2 | AB16: =SUM(P16:AA16) -> 65362.08 | AC16: =(Controls!$E$12*AC4*AC6)+(AC12) -> 5002.2 | AD16: =(Controls!$E$12*AD4*AD6)+(AD12) -> 4764 | AE16: =(Controls!$E$12*AE4*AE6)+(AE12) -> 5478.6 | AF16: =(Controls!$E$12*AF4*AF6)+(AF12) -> 4764 | AG16: =(Controls!$E$12*AG4*AG6)+(AG12) -> 5240.4 | AH16: =(Controls!$E$12*AH4*AH6)+(AH12) -> 5240.4 | AI16: =(Controls!$E$12*AI4*AI6)+(AI12) -> 4764 | AJ16: =(Controls!$E$12*AJ4*AJ6)+(AJ12) -> 5478.6 | ... AN16: =(Controls!$E$12*AN4*AN6)+(AN12) -> 3811.2 | AO16: =SUM(AC16:AN16) -> 59311.8
A17: Utilization % of billable hours | C17: 0.8 | D17: 0.8 | E17: 0.8 | F17: 0.8 | G17: 0.8 | H17: 0.8 | I17: 0.8 | J17: 0.8 | K17: 0.8 | L17: 0.8 | M17: 0.8 | N17: 0.8 | O17: =AVERAGE(C17:N17) -> 0.8 | P17: 0.8 | Q17: 0.8 | R17: 0.8 | S17: 0.8 | T17: 0.8 | U17: 0.8 | V17: 0.8 | W17: 0.8 | X17: 0.8 | Y17: 0.8 | Z17: 0.8 | AA17: 0.8 | AB17: =AVERAGE(P17:AA17) -> 0.8 | AC17: 0.8 | AD17: 0.8 | AE17: 0.8 | AF17: 0.8 | AG17: 0.8 | AH17: 0.8 | AI17: 0.8 | AJ17: 0.8 | AK17: 0.8 | AL17: 0.8 | AM17: 0.8 | AN17: 0.8 | AO17: =AVERAGE(AC17:AN17) -> 0.8
A18: Correct number of 100% Technicians adding vlaue | C18: =C4*C17 -> 20.8 | D18: =D4*D17 -> 20.8 | E18: =E4*E17 -> 20.8 | F18: =F4*F17 -> 20.8 | G18: =G4*G17 -> 20.8 | H18: =H4*H17 -> 20.8 | I18: =I4*I17 -> 20.8 | J18: =J4*J17 -> 20.8 | ... N18: =N4*N17 -> 20.8 | O18: =AVERAGE(C18:N18) -> 20.8 | P18: =P4*P17 -> 24 | Q18: =Q4*Q17 -> 28.8 | R18: =R4*R17 -> 28.8 | S18: =S4*S17 -> 28.8 | T18: =T4*T17 -> 28.8 | U18: =U4*U17 -> 28.8 | V18: =V4*V17 -> 28.8 | W18: =W4*W17 -> 24 | ... AA18: =AA4*AA17 -> 24 | AB18: =AVERAGE(P18:AA18) -> 26.4 | AC18: =AC4*AC17 -> 24 | AD18: =AD4*AD17 -> 24 | AE18: =AE4*AE17 -> 24 | AF18: =AF4*AF17 -> 24 | AG18: =AG4*AG17 -> 24 | AH18: =AH4*AH17 -> 24 | AI18: =AI4*AI17 -> 24 | AJ18: =AJ4*AJ17 -> 24 | ... AN18: =AN4*AN17 -> 24 | AO18: =AVERAGE(AC18:AN18) -> 24
A19: Total PTO hours loss | B19: -8 | C19: =$B$19*C4 -> -208 | D19: =$B$19*D4 -> -208 | E19: =$B$19*E4 -> -208 | F19: =$B$19*F4 -> -208 | G19: =$B$19*G4 -> -208 | H19: =$B$19*H4 -> -208 | I19: =$B$19*I4 -> -208 | J19: =$B$19*J4 -> -208 | ... N19: =$B$19*N4 -> -208 | O19: =SUM(C19:N19) -> -2496 | P19: =$B$19*P4 -> -240 | Q19: =$B$19*Q4 -> -288 | R19: =$B$19*R4 -> -288 | S19: =$B$19*S4 -> -288 | T19: =$B$19*T4 -> -288 | U19: =$B$19*U4 -> -288 | V19: =$B$19*V4 -> -288 | W19: =$B$19*W4 -> -240 | ... AA19: =$B$19*AA4 -> -240 | AB19: =SUM(P19:AA19) -> -3168 | AC19: =$B$19*AC4 -> -240 | AD19: =$B$19*AD4 -> -240 | AE19: =$B$19*AE4 -> -240 | AF19: =$B$19*AF4 -> -240 | AG19: =$B$19*AG4 -> -240 | AH19: =$B$19*AH4 -> -240 | AI19: =$B$19*AI4 -> -240 | AJ19: =$B$19*AJ4 -> -240 | ... AN19: =$B$19*AN4 -> -240 | AO19: =SUM(AC19:AN19) -> -2880
A20: Total calibrated billable hours | C20: =(C16*C17)+C19 -> 3260.192 | D20: =(D16*D17)+D19 -> 3095.04 | E20: =(E16*E17)+E19 -> 3590.496 | F20: =(F16*F17)+F19 -> 3095.04 | G20: =(G16*G17)+G19 -> 3425.344 | H20: =(H16*H17)+H19 -> 3425.344 | I20: =(I16*I17)+I19 -> 3095.04 | J20: =(J16*J17)+J19 -> 3590.496 | ... N20: =(N16*N17)+N19 -> 2434.432 | O20: =SUM(C20:N20) -> 38626.848 | P20: =(P16*P17)+P19 -> 3761.76 | Q20: =(Q16*Q17)+Q19 -> 4285.44 | R20: =(R16*R17)+R19 -> 4971.456 | S20: =(S16*S17)+S19 -> 4285.44 | T20: =(T16*T17)+T19 -> 4742.784 | U20: =(U16*U17)+U19 -> 4742.784 | V20: =(V16*V17)+V19 -> 4285.44 | W20: =(W16*W17)+W19 -> 4142.88 | ... AA20: =(AA16*AA17)+AA19 -> 2808.96 | AB20: =SUM(P20:AA20) -> 49121.664 | AC20: =(AC16*AC17)+AC19 -> 3761.76 | AD20: =(AD16*AD17)+AD19 -> 3571.2 | AE20: =(AE16*AE17)+AE19 -> 4142.88 | AF20: =(AF16*AF17)+AF19 -> 3571.2 | AG20: =(AG16*AG17)+AG19 -> 3952.32 | AH20: =(AH16*AH17)+AH19 -> 3952.32 | AI20: =(AI16*AI17)+AI19 -> 3571.2 | AJ20: =(AJ16*AJ17)+AJ19 -> 4142.88 | ... AN20: =(AN16*AN17)+AN19 -> 2808.96 | AO20: =SUM(AC20:AN20) -> 44569.44
A22: Costs
A23: Cost of holiday | C23: =$B$7*C4*C5 -> -11232 | D23: 0 | E23: 0 | F23: 0 | G23: =$B$7*G4*G5 -> -11232 | H23: 0 | I23: =$B$7*I4*I5 -> -11232 | J23: 0 | K23: 0 | L23: 0 | M23: =$B$7*M4*M5 -> -11232 | N23: =$B$7*N4*N5 -> -11232 | O23: 0 | P23: =$B$7*P4*P5 -> -12960 | Q23: 0 | R23: 0 | S23: 0 | T23: =$B$7*T4*T5 -> -15552 | U23: 0 | V23: =$B$7*V4*V5 -> -15552 | W23: 0 | X23: 0 | Y23: 0 | Z23: =$B$7*Z4*Z5 -> -12960 | AA23: =$B$7*AA4*AA5 -> -12960 | AB23: 0 | AC23: =$B$7*AC4*AC5 -> -12960 | AD23: 0 | AE23: 0 | AF23: 0 | AG23: =$B$7*AG4*AG5 -> -12960 | AH23: 0 | AI23: =$B$7*AI4*AI5 -> -12960 | AJ23: 0 | AK23: 0 | AL23: 0 | AM23: =$B$7*AM4*AM5 -> -12960 | AN23: =$B$7*AN4*AN5 -> -12960 | AO23: 0
A24: Average Daily MH Cost | B24: =Controls!D59 -> -54 | C24: =$B$24*C8 -> -11232 | D24: =$B$24*D8 -> -11232 | E24: =$B$24*E8 -> -11232 | F24: =$B$24*F8 -> -11232 | G24: =$B$24*G8 -> -11232 | H24: =$B$24*H8 -> -11232 | I24: =$B$24*I8 -> -11232 | J24: =$B$24*J8 -> -11232 | ... N24: =$B$24*N8 -> -11232 | O24: =SUM(C24:N24) -> -134784 | P24: =$B$24*P8 -> -12960 | Q24: =$B$24*Q8 -> -15552 | R24: =$B$24*R8 -> -15552 | S24: =$B$24*S8 -> -15552 | T24: =$B$24*T8 -> -15552 | U24: =$B$24*U8 -> -15552 | V24: =$B$24*V8 -> -15552 | W24: =$B$24*W8 -> -12960 | ... AA24: =$B$24*AA8 -> -12960 | AB24: =SUM(P24:AA24) -> -171072 | AC24: =$B$24*AC8 -> -12960 | AD24: =$B$24*AD8 -> -12960 | AE24: =$B$24*AE8 -> -12960 | AF24: =$B$24*AF8 -> -12960 | AG24: =$B$24*AG8 -> -12960 | AH24: =$B$24*AH8 -> -12960 | AI24: =$B$24*AI8 -> -12960 | AJ24: =$B$24*AJ8 -> -12960 | ... AN24: =$B$24*AN8 -> -12960 | AO24: =SUM(AC24:AN24) -> -155520
A25: Average Daily OT MH Cost | B25: =B24*1.5 -> -81 | C25: =$B$25*C11 -> -505.44 | D25: =$B$25*D11 -> -505.44 | E25: =$B$25*E11 -> -505.44 | F25: =$B$25*F11 -> -505.44 | G25: =$B$25*G11 -> -505.44 | H25: =$B$25*H11 -> -505.44 | I25: =$B$25*I11 -> -505.44 | J25: =$B$25*J11 -> -505.44 | ... N25: =$B$25*N11 -> -505.44 | O25: =SUM(C25:N25) -> -6065.28 | P25: =$B$25*P11 -> -583.2 | Q25: =$B$25*Q11 -> -699.84 | R25: =$B$25*R11 -> -699.84 | S25: =$B$25*S11 -> -699.84 | T25: =$B$25*T11 -> -699.84 | U25: =$B$25*U11 -> -699.84 | V25: =$B$25*V11 -> -699.84 | W25: =$B$25*W11 -> -583.2 | ... AA25: =$B$25*AA11 -> -583.2 | AB25: =SUM(P25:AA25) -> -7698.24 | AC25: =$B$25*AC11 -> -583.2 | AD25: =$B$25*AD11 -> -583.2 | AE25: =$B$25*AE11 -> -583.2 | AF25: =$B$25*AF11 -> -583.2 | AG25: =$B$25*AG11 -> -583.2 | AH25: =$B$25*AH11 -> -583.2 | AI25: =$B$25*AI11 -> -583.2 | AJ25: =$B$25*AJ11 -> -583.2 | ... AN25: =$B$25*AN11 -> -583.2 | AO25: =SUM(AC25:AN25) -> -6998.4
A26: Average Monthly MH cost | B26: =B24 -> -54 | C26: =C9*$B$26 -> -235872 | D26: =D9*$B$26 -> -224640 | E26: =E9*$B$26 -> -258336 | F26: =F9*$B$26 -> -224640 | G26: =G9*$B$26 -> -247104 | H26: =H9*$B$26 -> -247104 | I26: =I9*$B$26 -> -224640 | J26: =J9*$B$26 -> -258336 | ... N26: =N9*$B$26 -> -179712 | O26: =SUM(C26:N26) -> -2796768 | P26: =P9*$B$26 -> -272160 | Q26: =Q9*$B$26 -> -311040 | R26: =R9*$B$26 -> -357696 | S26: =S9*$B$26 -> -311040 | T26: =T9*$B$26 -> -342144 | U26: =U9*$B$26 -> -342144 | V26: =V9*$B$26 -> -311040 | W26: =W9*$B$26 -> -298080 | ... AA26: =AA9*$B$26 -> -207360 | AB26: =SUM(P26:AA26) -> -3556224 | AC26: =AC9*$B$26 -> -272160 | AD26: =AD9*$B$26 -> -259200 | AE26: =AE9*$B$26 -> -298080 | AF26: =AF9*$B$26 -> -259200 | AG26: =AG9*$B$26 -> -285120 | AH26: =AH9*$B$26 -> -285120 | AI26: =AI9*$B$26 -> -259200 | AJ26: =AJ9*$B$26 -> -298080 | ... AN26: =AN9*$B$26 -> -207360 | AO26: =SUM(AC26:AN26) -> -3227040
A27: Average Monthly Hour Cost | B27: =B25 -> -81 | C27: =$B$27*C12 -> -10614.24 | D27: =$B$27*D12 -> -10108.8 | E27: =$B$27*E12 -> -11625.12 | F27: =$B$27*F12 -> -10108.8 | G27: =$B$27*G12 -> -11119.68 | H27: =$B$27*H12 -> -11119.68 | I27: =$B$27*I12 -> -10108.8 | J27: =$B$27*J12 -> -11625.12 | ... N27: =$B$27*N12 -> -8087.04 | O27: =SUM(C27:N27) -> -125854.56 | P27: =$B$27*P12 -> -12247.2 | Q27: =$B$27*Q12 -> -13996.8 | R27: =$B$27*R12 -> -16096.32 | S27: =$B$27*S12 -> -13996.8 | T27: =$B$27*T12 -> -15396.48 | U27: =$B$27*U12 -> -15396.48 | V27: =$B$27*V12 -> -13996.8 | W27: =$B$27*W12 -> -13413.6 | ... AA27: =$B$27*AA12 -> -9331.2 | AB27: =SUM(P27:AA27) -> -160030.08 | AC27: =$B$27*AC12 -> -12247.2 | AD27: =$B$27*AD12 -> -11664 | AE27: =$B$27*AE12 -> -13413.6 | AF27: =$B$27*AF12 -> -11664 | AG27: =$B$27*AG12 -> -12830.4 | AH27: =$B$27*AH12 -> -12830.4 | AI27: =$B$27*AI12 -> -11664 | AJ27: =$B$27*AJ12 -> -13413.6 | ... AN27: =$B$27*AN12 -> -9331.2 | AO27: =SUM(AC27:AN27) -> -145216.8
A28: Executive Overhead | O28: =SUM(C28:N28) -> 0 | AB28: =SUM(P28:AA28) -> 0 | AO28: =SUM(AC28:AN28) -> 0
A29: Non-billable investments Sam S. | O29: =SUM(C29:N29) -> 0 | AB29: =SUM(P29:AA29) -> 0 | AO29: =SUM(AC29:AN29) -> 0
A30: Detailer / Line service Lead | O30: =SUM(C30:N30) -> 0 | AB30: =SUM(P30:AA30) -> 0 | AO30: =SUM(AC30:AN30) -> 0
A31: Detailer / Line service | O31: =SUM(C31:N31) -> 0 | AB31: =SUM(P31:AA31) -> 0 | AO31: =SUM(AC31:AN31) -> 0
A32: Parts Clerk | O32: =SUM(C32:N32) -> 0 | AB32: =SUM(P32:AA32) -> 0 | AO32: =SUM(AC32:AN32) -> 0
A33: Shop Manager | O33: =SUM(C33:N33) -> 0 | AB33: =SUM(P33:AA33) -> 0 | AO33: =SUM(AC33:AN33) -> 0
A34: Total labor cost | C34: =SUM(C26,C27,C28,C29,C30,C32) -> -246486.24 | D34: =SUM(D26,D27,D28,D29,D30,D32) -> -234748.8 | E34: =SUM(E26,E27,E28,E29,E30,E32) -> -269961.12 | F34: =SUM(F26,F27,F28,F29,F30,F32) -> -234748.8 | G34: =SUM(G26,G27,G28,G29,G30,G32) -> -258223.68 | H34: =SUM(H26,H27,H28,H29,H30,H32) -> -258223.68 | I34: =SUM(I26,I27,I28,I29,I30,I32) -> -234748.8 | J34: =SUM(J26,J27,J28,J29,J30,J32) -> -269961.12 | ... N34: =SUM(N26,N27,N28,N29,N30,N32) -> -187799.04 | O34: =SUM(C34:N34) -> -2922622.6 | P34: =SUM(P26,P27,P28,P29,P30,P32) -> -284407.2 | Q34: =SUM(Q26,Q27,Q28,Q29,Q30,Q32) -> -325036.8 | R34: =SUM(R26,R27,R28,R29,R30,R32) -> -373792.32 | S34: =SUM(S26,S27,S28,S29,S30,S32) -> -325036.8 | T34: =SUM(T26,T27,T28,T29,T30,T32) -> -357540.48 | U34: =SUM(U26,U27,U28,U29,U30,U32) -> -357540.48 | V34: =SUM(V26,V27,V28,V29,V30,V32) -> -325036.8 | W34: =SUM(W26,W27,W28,W29,W30,W32) -> -311493.6 | ... AA34: =SUM(AA26,AA27,AA28,AA29,AA30,AA32) -> -216691.2 | AB34: =SUM(P34:AA34) -> -3716254.1 | AC34: =SUM(AC26,AC27,AC28,AC29,AC30,AC32) -> -284407.2 | AD34: =SUM(AD26,AD27,AD28,AD29,AD30,AD32) -> -270864 | AE34: =SUM(AE26,AE27,AE28,AE29,AE30,AE32) -> -311493.6 | AF34: =SUM(AF26,AF27,AF28,AF29,AF30,AF32) -> -270864 | AG34: =SUM(AG26,AG27,AG28,AG29,AG30,AG32) -> -297950.4 | AH34: =SUM(AH26,AH27,AH28,AH29,AH30,AH32) -> -297950.4 | AI34: =SUM(AI26,AI27,AI28,AI29,AI30,AI32) -> -270864 | AJ34: =SUM(AJ26,AJ27,AJ28,AJ29,AJ30,AJ32) -> -311493.6 | ... AN34: =SUM(AN26,AN27,AN28,AN29,AN30,AN32) -> -216691.2 | AO34: =SUM(AC34:AN34) -> -3372256.8

Sheet Work History
A1: BJC | G1: Avex TBM | H1: AVEX TBM | I1: Part 91 - Turbo Prop | J1: Part 91 - Turbo Prop | K1: Part 121 - Turbo Prop | L1: Part 121 - Turbo Prop | M1: Part 135 -Turbo Prop | N1: Part 135 -Turbo Prop | O1: Part 145 - Turbo Prop | P1: Part 145 - Turbo Prop | Q1: Part 91 - Jet | R1: Part 91 - Jet | S1: Part 121 - Jet | T1: Part 121 - Jet | U1: Part 135 - Jet | V1: Part 135 - Jet | W1: Part 145 - Jet | X1: Part 145 - Jet | Y1: Part 91 - Piston | Z1: Part 91 - Piston | AA1: Part 121 - Piston | AB1: Part 121 - Piston | AC1: Part 135 - Piston | AD1: Part 135 - Piston | AE1: Part 145 - Piston | AF1: Part 145 - Piston | AG1: Millitary Helicopter | AH1: Millitary Helicopter | AI1: Millitary Fixed wing | AJ1: Millitary Fixed wing | AK1: Expirimental GA | AL1: Expirimental GA | AM1: PT6 | AN1: PT6
A2: RATE | D2: True Total | E2: Corrected Totals | G2: EXP YRS | H2: 1 | I2: EXP | J2: 0.8 | K2: EXP | L2: 0.7 | M2: EXP | N2: 0.8 | O2: EXP | P2: 0.8 | Q2: EXP | R2: 0.7 | S2: EXP | T2: 0.6 | U2: EXP | V2: 0.7 | W2: EXP | X2: 0.8 | Y2: EXP | Z2: 0.6 | AA2: EXP | AB2: 0.5 | AC2: EXP | AD2: 0.5 | AE2: EXP | AF2: 0.5 | AG2: EXP | AH2: 0.3 | AI2: EXP | AJ2: 0.4 | AK2: EXP | AL2: 0.5 | AM2: EXP | AN2: 0.7
A4: Column1 | B4: Billing growth class | C4: Column2 | D4: Column3 | E4: Column4 | F4: Column5 | G4: Column6 | H4: Column7 | I4: Column8 | J4: Column9 | K4: Column10 | L4: Column11 | M4: Column12 | N4: Column13 | O4: Column14 | P4: Column15 | Q4: Column16 | R4: Column17 | S4: Column18 | T4: Column19 | U4: Column20 | V4: Column21 | W4: Column22 | X4: Column23 | Y4: Column24 | Z4: Column25 | AA4: Column26 | AB4: Column27 | AC4: Column28 | AD4: Column29 | AE4: Column30 | AF4: Column31 | AG4: Column32 | AH4: Column33 | AI4: Column34 | AJ4: Column35 | AK4: Column36 | AL4: Column37 | AM4: Column38 | AN4: Column39
A5: Sam Sandifer | B5: High | C5: DOM | D5: 8
A6: Sam Perez | B6: High | C6: SM | D6: 9
A7: Joe Vigil | B7: High | C7: AP/AV | D7: 8
A8: mech 1 | B8: High | C8: AP | D8: 1.5
A9: mech 2 | B9: High | C9: AP | D9: 1.5
A10: mech 3 | B10: Medium | C10: AP | D10: 0
A11: Mech 4 | B11: Medium | C11: AP | D11: 0
A12: Detailer/ line | B12: Low | C12: Det | D12: 0
A24: Totals | D24: =SUM(D5:D23) -> 28 | E24: =SUM(E5:E23) -> 0 | G24: =SUM(G5:G23) -> 0
A25: Averages | D25: =AVERAGE(D5:D23) -> 3.5 | E25: =AVERAGE(E5:E23) -> #DIV/0! | G25: =SUM(G5:G23)/20 -> 0
AP27: Add relavent experience prior to avex to this workseet, it is currently incomplete and has placeholders (CMA)
A29: SLC | G29: Avex TBM | H29: AVEX TBM | I29: Part 91 - Turbo Prop | J29: Part 91 - Turbo Prop | K29: Part 121 - Turbo Prop | L29: Part 121 - Turbo Prop | M29: Part 135 -Turbo Prop | N29: Part 135 -Turbo Prop | O29: Part 145 - Turbo Prop | P29: Part 145 - Turbo Prop | Q29: Part 91 - Jet | R29: Part 91 - Jet | S29: Part 121 - Jet | T29: Part 121 - Jet | U29: Part 135 - Jet | V29: Part 135 - Jet | W29: Part 145 - Jet | X29: Part 145 - Jet | Y29: Part 91 - Piston | Z29: Part 91 - Piston | AA29: Part 121 - Piston | AB29: Part 121 - Piston | AC29: Part 135 - Piston | AD29: Part 135 - Piston | AE29: Part 145 - Piston | AF29: Part 145 - Piston | AG29: Millitary Helicopter | AH29: Millitary Helicopter | AI29: Millitary Fixed wing | AJ29: Millitary Fixed wing | AK29: Expirimental GA | AL29: Expirimental GA | AM29: PT6 | AN29: PT6
A30: RATE | D30: True Total | E30: Corrected Totals | G30: EXP YRS | H30: 1 | I30: EXP | J30: 0.8 | K30: EXP | L30: 0.7 | M30: EXP | N30: 0.8 | O30: EXP | P30: 0.8 | Q30: EXP | R30: 0.7 | S30: EXP | T30: 0.6 | U30: EXP | V30: 0.7 | W30: EXP | X30: 0.8 | Y30: EXP | Z30: 0.6 | AA30: EXP | AB30: 0.5 | AC30: EXP | AD30: 0.5 | AE30: EXP | AF30: 0.5 | AG30: EXP | AH30: 0.3 | AI30: EXP | AJ30: 0.4 | AK30: EXP | AL30: 0.5 | AM30: EXP | AN30: 0.7
A32: Name | B32: Billing growth class | C32: Column2 | D32: Column3 | E32: Column4 | F32: Column5 | G32: Column6 | H32: Column7 | I32: Column8 | J32: Column9 | K32: Column10 | L32: Column11 | M32: Column12 | N32: Column13 | O32: Column14 | P32: Column15 | Q32: Column16 | R32: Column17 | S32: Column18 | T32: Column19 | U32: Column20 | V32: Column21 | W32: Column22 | X32: Column23 | Y32: Column24 | Z32: Column25 | AA32: Column26 | AB32: Column27 | AC32: Column28 | AD32: Column29 | AE32: Column30 | AF32: Column31 | AG32: Column32 | AH32: Column33 | AI32: Column34 | AJ32: Column35 | AK32: Column36 | AL32: Column37 | AM32: Column38 | AN32: Column39
L33: =K33*L$2 -> 0 | N33: =M33*N$2 -> 0 | P33: =O33*P$2 -> 0 | R33: =Q33*R$2 -> 0 | T33: =S33*T$2 -> 0 | V33: =U33*V$2 -> 0 | X33: =W33*X$2 -> 0 | Z33: =Y33*Z$2 -> 0 | AB33: =AA33*AB$2 -> 0 | AD33: =AC33*AD$2 -> 0 | AF33: =AE33*AF$2 -> 0 | AH33: =AG33*AH$2 -> 0 | AJ33: =AI33*AJ$2 -> 0 | AL33: =AK33*AL$2 -> 0 | AN33: =AM33*AN$2 -> 0
L34: =K34*L$2 -> 0 | N34: =M34*N$2 -> 0 | P34: =O34*P$2 -> 0 | R34: =Q34*R$2 -> 0 | T34: =S34*T$2 -> 0 | V34: =U34*V$2 -> 0 | X34: =W34*X$2 -> 0 | Z34: =Y34*Z$2 -> 0 | AB34: =AA34*AB$2 -> 0 | AD34: =AC34*AD$2 -> 0 | AF34: =AE34*AF$2 -> 0 | AH34: =AG34*AH$2 -> 0 | AJ34: =AI34*AJ$2 -> 0 | AL34: =AK34*AL$2 -> 0 | AN34: =AM34*AN$2 -> 0
L35: =K35*L$2 -> 0 | N35: =M35*N$2 -> 0 | P35: =O35*P$2 -> 0 | R35: =Q35*R$2 -> 0 | T35: =S35*T$2 -> 0 | V35: =U35*V$2 -> 0 | X35: =W35*X$2 -> 0 | Z35: =Y35*Z$2 -> 0 | AB35: =AA35*AB$2 -> 0 | AD35: =AC35*AD$2 -> 0 | AF35: =AE35*AF$2 -> 0 | AH35: =AG35*AH$2 -> 0 | AJ35: =AI35*AJ$2 -> 0 | AL35: =AK35*AL$2 -> 0 | AN35: =AM35*AN$2 -> 0
L36: =K36*L$2 -> 0 | N36: =M36*N$2 -> 0 | P36: =O36*P$2 -> 0 | R36: =Q36*R$2 -> 0 | T36: =S36*T$2 -> 0 | V36: =U36*V$2 -> 0 | X36: =W36*X$2 -> 0 | Z36: =Y36*Z$2 -> 0 | AB36: =AA36*AB$2 -> 0 | AD36: =AC36*AD$2 -> 0 | AF36: =AE36*AF$2 -> 0 | AH36: =AG36*AH$2 -> 0 | AJ36: =AI36*AJ$2 -> 0 | AL36: =AK36*AL$2 -> 0 | AN36: =AM36*AN$2 -> 0
L37: =K37*L$2 -> 0 | N37: =M37*N$2 -> 0 | P37: =O37*P$2 -> 0 | R37: =Q37*R$2 -> 0 | T37: =S37*T$2 -> 0 | V37: =U37*V$2 -> 0 | X37: =W37*X$2 -> 0 | Z37: =Y37*Z$2 -> 0 | AB37: =AA37*AB$2 -> 0 | AD37: =AC37*AD$2 -> 0 | AF37: =AE37*AF$2 -> 0 | AH37: =AG37*AH$2 -> 0 | AJ37: =AI37*AJ$2 -> 0 | AL37: =AK37*AL$2 -> 0 | AN37: =AM37*AN$2 -> 0
L38: =K38*L$2 -> 0 | N38: =M38*N$2 -> 0 | P38: =O38*P$2 -> 0 | R38: =Q38*R$2 -> 0 | T38: =S38*T$2 -> 0 | V38: =U38*V$2 -> 0 | X38: =W38*X$2 -> 0 | Z38: =Y38*Z$2 -> 0 | AB38: =AA38*AB$2 -> 0 | AD38: =AC38*AD$2 -> 0 | AF38: =AE38*AF$2 -> 0 | AH38: =AG38*AH$2 -> 0 | AJ38: =AI38*AJ$2 -> 0 | AL38: =AK38*AL$2 -> 0 | AN38: =AM38*AN$2 -> 0
L39: =K39*L$2 -> 0 | N39: =M39*N$2 -> 0 | P39: =O39*P$2 -> 0 | R39: =Q39*R$2 -> 0 | T39: =S39*T$2 -> 0 | V39: =U39*V$2 -> 0 | X39: =W39*X$2 -> 0 | Z39: =Y39*Z$2 -> 0 | AB39: =AA39*AB$2 -> 0 | AD39: =AC39*AD$2 -> 0 | AF39: =AE39*AF$2 -> 0 | AH39: =AG39*AH$2 -> 0 | AJ39: =AI39*AJ$2 -> 0 | AL39: =AK39*AL$2 -> 0 | AN39: =AM39*AN$2 -> 0
L40: =K40*L$2 -> 0 | N40: =M40*N$2 -> 0 | P40: =O40*P$2 -> 0 | R40: =Q40*R$2 -> 0 | T40: =S40*T$2 -> 0 | V40: =U40*V$2 -> 0 | X40: =W40*X$2 -> 0 | Z40: =Y40*Z$2 -> 0 | AB40: =AA40*AB$2 -> 0 | AD40: =AC40*AD$2 -> 0 | AF40: =AE40*AF$2 -> 0 | AH40: =AG40*AH$2 -> 0 | AJ40: =AI40*AJ$2 -> 0 | AL40: =AK40*AL$2 -> 0 | AN40: =AM40*AN$2 -> 0
L41: =K41*L$2 -> 0 | N41: =M41*N$2 -> 0 | P41: =O41*P$2 -> 0 | R41: =Q41*R$2 -> 0 | T41: =S41*T$2 -> 0 | V41: =U41*V$2 -> 0 | X41: =W41*X$2 -> 0 | Z41: =Y41*Z$2 -> 0 | AB41: =AA41*AB$2 -> 0 | AD41: =AC41*AD$2 -> 0 | AF41: =AE41*AF$2 -> 0 | AH41: =AG41*AH$2 -> 0 | AJ41: =AI41*AJ$2 -> 0 | AL41: =AK41*AL$2 -> 0 | AN41: =AM41*AN$2 -> 0
L42: =K42*L$2 -> 0 | N42: =M42*N$2 -> 0 | P42: =O42*P$2 -> 0 | R42: =Q42*R$2 -> 0 | T42: =S42*T$2 -> 0 | V42: =U42*V$2 -> 0 | X42: =W42*X$2 -> 0 | Z42: =Y42*Z$2 -> 0 | AB42: =AA42*AB$2 -> 0 | AD42: =AC42*AD$2 -> 0 | AF42: =AE42*AF$2 -> 0 | AH42: =AG42*AH$2 -> 0 | AJ42: 4 | AL42: =AK42*AL$2 -> 0 | AN42: =AM42*AN$2 -> 0
L43: =K43*L$2 -> 0 | N43: =M43*N$2 -> 0 | P43: =O43*P$2 -> 0 | R43: =Q43*R$2 -> 0 | T43: =S43*T$2 -> 0 | V43: =U43*V$2 -> 0 | X43: =W43*X$2 -> 0 | Z43: =Y43*Z$2 -> 0 | AB43: =AA43*AB$2 -> 0 | AD43: =AC43*AD$2 -> 0 | AF43: =AE43*AF$2 -> 0 | AH43: =AG43*AH$2 -> 0 | AJ43: =AI43*AJ$2 -> 0 | AL43: =AK43*AL$2 -> 0 | AN43: =AM43*AN$2 -> 0
L44: =K44*L$2 -> 0 | N44: =M44*N$2 -> 0 | P44: =O44*P$2 -> 0 | R44: =Q44*R$2 -> 0 | T44: =S44*T$2 -> 0 | V44: =U44*V$2 -> 0 | X44: =W44*X$2 -> 0 | Z44: =Y44*Z$2 -> 0 | AB44: =AA44*AB$2 -> 0 | AD44: =AC44*AD$2 -> 0 | AF44: =AE44*AF$2 -> 0 | AH44: =AG44*AH$2 -> 0 | AJ44: =AI44*AJ$2 -> 0 | AL44: =AK44*AL$2 -> 0 | AN44: =AM44*AN$2 -> 0
L45: =K45*L$2 -> 0 | N45: =M45*N$2 -> 0 | P45: =O45*P$2 -> 0 | R45: =Q45*R$2 -> 0 | T45: =S45*T$2 -> 0 | V45: =U45*V$2 -> 0 | X45: =W45*X$2 -> 0 | Z45: =Y45*Z$2 -> 0 | AB45: =AA45*AB$2 -> 0 | AD45: =AC45*AD$2 -> 0 | AF45: =AE45*AF$2 -> 0 | AH45: =AG45*AH$2 -> 0 | AJ45: =AI45*AJ$2 -> 0 | AL45: =AK45*AL$2 -> 0 | AN45: =AM45*AN$2 -> 0
L46: =K46*L$2 -> 0 | N46: =M46*N$2 -> 0 | P46: =O46*P$2 -> 0 | R46: =Q46*R$2 -> 0 | T46: =S46*T$2 -> 0 | V46: =U46*V$2 -> 0 | X46: =W46*X$2 -> 0 | Z46: =Y46*Z$2 -> 0 | AB46: =AA46*AB$2 -> 0 | AD46: =AC46*AD$2 -> 0 | AF46: =AE46*AF$2 -> 0 | AH46: =AG46*AH$2 -> 0 | AJ46: =AI46*AJ$2 -> 0 | AL46: =AK46*AL$2 -> 0 | AN46: =AM46*AN$2 -> 0
L47: =K47*L$2 -> 0 | N47: =M47*N$2 -> 0 | P47: =O47*P$2 -> 0 | R47: =Q47*R$2 -> 0 | T47: =S47*T$2 -> 0 | V47: =U47*V$2 -> 0 | X47: =W47*X$2 -> 0 | Z47: =Y47*Z$2 -> 0 | AB47: =AA47*AB$2 -> 0 | AD47: =AC47*AD$2 -> 0 | AF47: =AE47*AF$2 -> 0 | AH47: =AG47*AH$2 -> 0 | AJ47: =AI47*AJ$2 -> 0 | AL47: =AK47*AL$2 -> 0 | AN47: =AM47*AN$2 -> 0
L48: =K48*L$2 -> 0 | N48: =M48*N$2 -> 0 | P48: =O48*P$2 -> 0 | R48: =Q48*R$2 -> 0 | T48: =S48*T$2 -> 0 | V48: =U48*V$2 -> 0 | X48: =W48*X$2 -> 0 | Z48: =Y48*Z$2 -> 0 | AB48: =AA48*AB$2 -> 0 | AD48: =AC48*AD$2 -> 0 | AF48: =AE48*AF$2 -> 0 | AH48: =AG48*AH$2 -> 0 | AJ48: =AI48*AJ$2 -> 0 | AL48: =AK48*AL$2 -> 0 | AN48: =AM48*AN$2 -> 0
L49: =K49*L$2 -> 0 | N49: =M49*N$2 -> 0 | P49: =O49*P$2 -> 0 | R49: =Q49*R$2 -> 0 | T49: =S49*T$2 -> 0 | V49: =U49*V$2 -> 0 | X49: =W49*X$2 -> 0 | Z49: =Y49*Z$2 -> 0 | AB49: =AA49*AB$2 -> 0 | AD49: =AC49*AD$2 -> 0 | AF49: =AE49*AF$2 -> 0 | AH49: =AG49*AH$2 -> 0 | AJ49: =AI49*AJ$2 -> 0 | AL49: =AK49*AL$2 -> 0 | AN49: =AM49*AN$2 -> 0
L50: =K50*L$2 -> 0 | N50: =M50*N$2 -> 0 | P50: =O50*P$2 -> 0 | R50: =Q50*R$2 -> 0 | T50: =S50*T$2 -> 0 | V50: =U50*V$2 -> 0 | X50: =W50*X$2 -> 0 | Z50: =Y50*Z$2 -> 0 | AB50: =AA50*AB$2 -> 0 | AD50: =AC50*AD$2 -> 0 | AF50: =AE50*AF$2 -> 0 | AH50: =AG50*AH$2 -> 0 | AJ50: =AI50*AJ$2 -> 0 | AL50: =AK50*AL$2 -> 0 | AN50: =AM50*AN$2 -> 0
A51: Totals | D51: =SUM(D33:D50) -> 0 | E51: =SUM(E33:E50) -> 0 | G51: =SUM(G33:G50) -> 0
A52: Averages | D52: =AVERAGE(D33:D50) -> #DIV/0! | E52: =AVERAGE(E33:E50) -> #DIV/0! | G52: =SUM(G33:G50)/20 -> 0
A59: Month | B59: 10th
A60: 1 | B60: =A60/12 -> 0.083333333
A61: 2 | B61: =A61/12 -> 0.16666667
A62: 3 | B62: =A62/12 -> 0.25
A63: 4 | B63: =A63/12 -> 0.33333333
A64: 5 | B64: =A64/12 -> 0.41666667
A65: 6 | B65: =A65/12 -> 0.5
A66: 7 | B66: =A66/12 -> 0.58333333
A67: 8 | B67: =A67/12 -> 0.66666667
A68: 9 | B68: =A68/12 -> 0.75
A69: 10 | B69: =A69/12 -> 0.83333333
A70: 11 | B70: =A70/12 -> 0.91666667
A71: 12 | B71: =A71/12 -> 1
A79: Experience type | B79: Converiosn rate
A80: Part 91 - Turbo Prop | B80: 0.8
A81: Part 121 - Turbo Prop | B81: 0.7
A82: Part 135 -Turbo Prop | B82: 0.8
A83: Part 145 - Turbo Prop | B83: 0.8
A84: Part 91 - Jet | B84: 0.7
A85: Part 121 - Jet | B85: 0.6
A86: Part 135 - Jet | B86: 0.7
A87: Part 145 - Jet | B87: 0.8
A88: Part 91 - Piston | B88: 0.6
A89: Part 121 - Piston | B89: 0.5
A90: Part 135 - Piston | B90: 0.5
A91: Part 145 - Piston | B91: 0.5
... A95: PT6 Engine | B95: 0.7

Sheet TEAMGROWTH
A3: =Controls!C2 -> Billable time worksheet | E3: Efficiency % change from low to average on standard work
B4: =Controls!D3 -> Mins | C4: =Controls!E3 -> Hours | E4: 0.16711807 | F4: =(E4-1)*-1 -> 0.83288193
A5: =Controls!C4 -> Time in day | B5: =Controls!D4 -> 480 | C5: =Controls!E4 -> 8
A6: =Controls!C5 -> Daily Breaks | B6: =Controls!D5 -> 30 | C6: =Controls!E5 -> 0.5
A7: =Controls!C6 -> Daily Lunches | B7: =Controls!D6 -> 0 | C7: =Controls!E6 -> 0
A8: =Controls!C7 -> Daily Clean up | B8: =Controls!D7 -> 15 | C8: =Controls!E7 -> 0.25
A9: =Controls!C8 -> Daily Meetings | B9: =Controls!D8 -> 9 | C9: =Controls!E8 -> 0.15
A10: =Controls!C9 -> Total reduction | B10: =Controls!D9 -> -54 | C10: =Controls!E9 -> -0.9
A12: =Controls!C11 -> Daily billiable | B12: =Controls!D11 -> -18 | C12: =Controls!E11 -> -0.3
A13: =Controls!C12 -> Total billable time in day | B13: =Controls!D12 -> 462 | C13: =Controls!E12 -> 7.7
A14: =Controls!C13 -> Total billable time with OT | B14: =Controls!D13 -> 475.86 | C14: =Controls!E13 -> 7.931
A16: =Controls!C15 -> Overtime Assumption | C16: =Controls!E15 -> 0.03
A18: Total days in 2023 | B18: ='Man Hours & Costs'!O6 -> 249
A19: Average days per month | B19: =B18/12 -> 20.75
A21: Total number of technicians in BJC | B21: =COUNTA(D27:D41) -> 8
A22: Total number of technicians in SLC | B22: =COUNTA(D58:D67) -> 1
A26: Months to hit fully billiable target | B26: Target to High work est | C26: Current | D26: Name | E26: Billing growth class | F26: Position | G26: Billing Rate Growth | H26: Starting Efficientcy | I26: Overall Job Reduction | J26: Column1 | K26: Jan Rate | L26: Jan BH | M26: Feb Rate | N26: Feb BH | O26: Mar Rate | P26: Mar BH | Q26: Apr Rate | R26: Apr BH | S26: May Rate | T26: May BH | U26: Jun Rate | V26: Jun BH | W26: Jul Rate | X26: Jul BH | Y26: Aug Rate | Z26: Aug BH | AA26: Sep Rate | AB26: Sep BH | AC26: Oct Rate | AD26: Oct BH | AE26: Nov Rate | AF26: Nov BH | AG26: Dec Rate | AH26: Dec BH | AI26: Column2
A27: =(B27-C27)*12 -> 9 | B27: 0.75 | C27: ='Work History'!H9 -> 0 | D27: Avionics lead | E27: High | F27: AP | G27: =Controls!$G$20 -> 0.125 | H27: 1 | I27: 1 | K27: Avg | L27: =($C$14*$B$19) -> 164.56825 | M27: Avg | N27: =($C$14*$B$19) -> 164.56825 | O27: Avg | P27: =($C$14*$B$19) -> 164.56825 | Q27: Avg | R27: =($C$14*$B$19) -> 164.56825 | S27: Avg | T27: =($C$14*$B$19) -> 164.56825 | U27: Avg | V27: =($C$14*$B$19) -> 164.56825 | W27: Avg | X27: =($C$14*$B$19) -> 164.56825 | Y27: Avg | Z27: =($C$14*$B$19) -> 164.56825 | AA27: Avg | AB27: =($C$14*$B$19) -> 164.56825 | AC27: Avg | AD27: =($C$14*$B$19) -> 164.56825 | AE27: Avg | AF27: =($C$14*$B$19) -> 164.56825 | AG27: Avg | AH27: =($C$14*$B$19) -> 164.56825
A28: =(B28-C28)*12 -> 9 | B28: 0.75 | C28: ='Work History'!H8 -> 0 | D28: Lead | E28: High | F28: AP | G28: =Controls!$G$20 -> 0.125 | H28: 1 | I28: =Controls!D29 -> 0.5 | K28: Avg | L28: =($C$14*$B$19)*$I$28 -> 82.284125 | M28: Avg | N28: =($C$14*$B$19)*$I$28 -> 82.284125 | O28: Avg | P28: =($C$14*$B$19)*$I$28 -> 82.284125 | Q28: Avg | R28: =($C$14*$B$19)*$I$28 -> 82.284125 | S28: Avg | T28: =($C$14*$B$19)*$I$28 -> 82.284125 | U28: Avg | V28: =($C$14*$B$19)*$I$28 -> 82.284125 | W28: Avg | X28: =($C$14*$B$19)*$I$28 -> 82.284125 | Y28: Avg | Z28: =($C$14*$B$19)*$I$28 -> 82.284125 | AA28: Avg | AB28: =($C$14*$B$19)*$I$28 -> 82.284125 | AC28: Avg | AD28: =($C$14*$B$19)*$I$28 -> 82.284125 | AE28: Avg | AF28: =($C$14*$B$19)*$I$28 -> 82.284125 | AG28: Avg | AH28: =($C$14*$B$19)*$I$28 -> 82.284125
A29: =(B29-C29)*12 -> 9 | B29: 0.75 | C29: ='Work History'!H12 -> 0 | D29: Joe Vigil AP/AV | E29: High | F29: AP | G29: =Controls!$G$20 -> 0.125 | H29: 1 | I29: 1 | K29: Avg | L29: =($C$14*$B$19) -> 164.56825 | M29: Avg | N29: =($C$14*$B$19) -> 164.56825 | O29: Avg | P29: =($C$14*$B$19) -> 164.56825 | Q29: Avg | R29: =($C$14*$B$19) -> 164.56825 | S29: Avg | T29: =($C$14*$B$19) -> 164.56825 | U29: Avg | V29: =($C$14*$B$19) -> 164.56825 | W29: Avg | X29: =($C$14*$B$19) -> 164.56825 | Y29: Avg | Z29: =($C$14*$B$19) -> 164.56825 | AA29: Avg | AB29: =($C$14*$B$19) -> 164.56825 | AC29: Avg | AD29: =($C$14*$B$19) -> 164.56825 | AE29: Avg | AF29: =($C$14*$B$19) -> 164.56825 | AG29: Avg | AH29: =($C$14*$B$19) -> 164.56825
A30: =(B30-C30)*12 -> 9 | B30: 0.75 | C30: ='Work History'!H5 -> 0 | D30: X Mech 1, 1-3YR AP | E30: High | F30: AV CC | G30: =Controls!$G$20 -> 0.125 | H30: 0.7 | I30: 1 | K30: Avg | L30: =(($C$14*$B$19)*TEAMGROWTH!$H30)*TEAMGROWTH!$I30 -> 115.19777 | M30: Avg | N30: =L30*1.25 -> 143.99722 | O30: Avg | P30: =($C$14*$B$19) -> 164.56825 | Q30: Avg | R30: =P30 -> 164.56825 | S30: Avg | T30: =P30 -> 164.56825 | U30: Avg | V30: =T30 -> 164.56825 | W30: Avg | X30: =V30 -> 164.56825 | Y30: Avg | Z30: =X30 -> 164.56825 | AA30: Avg | AB30: =Z30 -> 164.56825 | AC30: Avg | AD30: =AB30 -> 164.56825 | AE30: Avg | AF30: =AD30 -> 164.56825 | AG30: Avg | AH30: =AF30 -> 164.56825
A31: =(B31-C31)*12 -> 9 | B31: 0.75 | C31: ='Work History'!H7 -> 0 | D31: X Mech 2, 1-3YR Entry AP | E31: High | F31: CC | G31: =Controls!$G$20 -> 0.125 | H31: 0.7 | I31: 1 | K31: Avg | L31: =(($C$14*$B$19)*TEAMGROWTH!$H31)*TEAMGROWTH!$I31 -> 115.19777 | M31: Avg | N31: =L31*1.25 -> 143.99722 | O31: Avg | P31: =($C$14*$B$19) -> 164.56825 | Q31: Avg | R31: =P31 -> 164.56825 | S31: Avg | T31: =R31 -> 164.56825 | U31: Avg | V31: =T31 -> 164.56825 | W31: Avg | X31: =V31 -> 164.56825 | Y31: Avg | Z31: =X31 -> 164.56825 | AA31: Avg | AB31: =Z31 -> 164.56825 | AC31: Avg | AD31: =AB31 -> 164.56825 | AE31: Avg | AF31: =AD31 -> 164.56825 | AG31: Avg | AH31: =AF31 -> 164.56825
A32: =(B32-C32)*12 -> 9 | B32: 0.75 | C32: ='Work History'!H10 -> 0 | D32: X Mech 3, Entry AP | E32: Med | F32: CC | G32: =Controls!$G$20 -> 0.125 | H32: 0.7 | I32: 1 | K32: Avg | L32: =($C$14*$B$19)*TEAMGROWTH!$I$32*$H$32 -> 115.19777 | M32: Avg | N32: =L32*1.25 -> 143.99722 | O32: Avg | P32: =($C$14*$B$19) -> 164.56825 | Q32: Avg | R32: =P32 -> 164.56825 | S32: Avg | T32: =R32 -> 164.56825 | U32: Avg | V32: =T32 -> 164.56825 | W32: Avg | X32: =V32 -> 164.56825 | Y32: Avg | Z32: =X32 -> 164.56825 | AA32: Avg | AB32: =Z32 -> 164.56825 | AC32: Avg | AD32: =AB32 -> 164.56825 | AE32: Avg | AF32: =AD32 -> 164.56825 | AG32: Avg | AH32: =AF32 -> 164.56825
A33: =(B33-C33)*12 -> 9 | B33: 0.75 | C33: ='Work History'!H6 -> 0 | D33: X Mech 4, Entry AP | E33: Med | F33: CC | G33: =Controls!$G$20 -> 0.125 | H33: 0.6 | I33: 1 | K33: Avg | L33: =($C$14*$B$19)*TEAMGROWTH!$I33*H33 -> 98.74095 | M33: Avg | N33: =($C$14*$B$19)*TEAMGROWTH!$I$32*$H$32 -> 115.19777 | O33: Avg | P33: =N33*1.25 -> 143.99722 | Q33: Avg | R33: =($C$14*$B$19) -> 164.56825 | S33: Avg | T33: =R33 -> 164.56825 | U33: Avg | V33: =T33 -> 164.56825 | W33: Avg | X33: =V33 -> 164.56825 | Y33: Avg | Z33: =X33 -> 164.56825 | AA33: Avg | AB33: =Z33 -> 164.56825 | AC33: Avg | AD33: =AB33 -> 164.56825 | AE33: Avg | AF33: =AD33 -> 164.56825 | AG33: Avg | AH33: =AF33 -> 164.56825
A34: =(B34-C34)*12 -> 9.96 | B34: 0.83 | C34: ='Work History'!H11 -> 0 | D34: Detailer and line support | E34: High | F34: AP | G34: =Controls!$G$20 -> 0.125 | H34: 0.3 | I34: 1 | K34: Avg | L34: =($C$14*$B$19)*H34 -> 49.370475 | M34: Avg | N34: =L34 -> 49.370475 | O34: Avg | P34: =N34 -> 49.370475 | Q34: Avg | R34: =P34 -> 49.370475 | S34: Avg | T34: =R34 -> 49.370475 | U34: Avg | V34: =T34 -> 49.370475 | W34: Avg | X34: =V34 -> 49.370475 | Y34: Avg | Z34: =X34 -> 49.370475 | AA34: Avg | AB34: =Z34 -> 49.370475 | AC34: Avg | AD34: =AB34 -> 49.370475 | AE34: Avg | AF34: =AB34 -> 49.370475 | AG34: Avg | AH34: =AF34 -> 49.370475
J36: Avg | K36: =COUNTIF(K27:K34,"Avg") -> 8 | L36: Avg | M36: =COUNTIF(M27:M34,"Avg") -> 8 | N36: Avg | O36: =COUNTIF(O27:O34,"Avg") -> 8 | P36: Avg | Q36: =COUNTIF(Q27:Q34,"Avg") -> 8 | R36: Avg | S36: =COUNTIF(S27:S34,"Avg") -> 8 | T36: Avg | U36: =COUNTIF(U27:U34,"Avg") -> 8 | V36: Avg | W36: =COUNTIF(W27:W34,"Avg") -> 8 | X36: Avg | Y36: =COUNTIF(Y27:Y34,"Avg") -> 8 | Z36: Avg | AA36: =COUNTIF(AA27:AA34,"Avg") -> 8 | AB36: Avg | AC36: =COUNTIF(AC27:AC34,"Avg") -> 8 | AD36: Avg | AE36: =COUNTIF(AE27:AE34,"Avg") -> 8 | AF36: Avg | AG36: =COUNTIF(AG27:AG34,"Avg") -> 8
J37: Low | K37: =COUNTIF(K27:K34,"low") -> 0 | L37: Low | M37: =COUNTIF(M27:M34,"low") -> 0 | N37: Low | O37: =COUNTIF(O27:O34,"low") -> 0 | P37: Low | Q37: =COUNTIF(Q27:Q34,"low") -> 0 | R37: Low | S37: =COUNTIF(S27:S34,"low") -> 0 | T37: Low | U37: =COUNTIF(U27:U34,"low") -> 0 | V37: Low | W37: =COUNTIF(W27:W34,"low") -> 0 | X37: Low | Y37: =COUNTIF(Y27:Y34,"low") -> 0 | Z37: Low | AA37: =COUNTIF(AA27:AA34,"low") -> 0 | AB37: Low | AC37: =COUNTIF(AC27:AC34,"low") -> 0 | AD37: Low | AE37: =COUNTIF(AE27:AE34,"low") -> 0 | AF37: Low | AG37: =COUNTIF(AG27:AG34,"low") -> 0
K38: =K37/(K36+K37) -> 0 | L38: =((SUM(L27:L34)*K38))*($E$4)*-1 -> 0 | M38: =M37/(M36+M37) -> 0 | N38: =((SUM(N27:N34)*M38))*($E$4)*-1 -> 0 | O38: =O37/(O36+O37) -> 0 | P38: =((SUM(P27:P34)*O38))*($E$4)*-1 -> 0 | Q38: =Q37/(Q36+Q37) -> 0 | R38: =((SUM(R27:R34)*Q38))*($E$4)*-1 -> 0 | S38: =S37/(S36+S37) -> 0 | T38: =((SUM(T27:T34)*S38))*($E$4)*-1 -> 0 | U38: =U37/(U36+U37) -> 0 | V38: =((SUM(V27:V34)*U38))*($E$4)*-1 -> 0 | W38: =W37/(W36+W37) -> 0 | X38: =((SUM(X27:X34)*W38))*($E$4)*-1 -> 0 | Y38: =Y37/(Y36+Y37) -> 0 | Z38: =((SUM(Z27:Z34)*Y38))*($E$4)*-1 -> 0 | AA38: =AA37/(AA36+AA37) -> 0 | AB38: =((SUM(AB27:AB34)*AA38))*($E$4)*-1 -> 0 | AC38: =AC37/(AC36+AC37) -> 0 | AD38: =((SUM(AD27:AD34)*AC38))*($E$4)*-1 -> 0 | AE38: =AE37/(AE36+AE37) -> 0 | AF38: =((SUM(AF27:AF34)*AE38))*($E$4)*-1 -> 0 | AG38: =AG37/(AG36+AG37) -> 0 | AH38: =((SUM(AH27:AH34)*AG38))*($E$4)*-1 -> 0
I39: Total | L39: =SUM(L27:L38) -> 905.12537 | N39: =SUM(N27:N38) -> 1007.9805 | P39: =SUM(P27:P38) -> 1098.4931 | R39: =SUM(R27:R38) -> 1119.0641 | T39: =SUM(T27:T38) -> 1119.0641 | V39: =SUM(V27:V38) -> 1119.0641 | X39: =SUM(X27:X38) -> 1119.0641 | Z39: =SUM(Z27:Z38) -> 1119.0641 | AB39: =SUM(AB27:AB38) -> 1119.0641 | AD39: =SUM(AD27:AD38) -> 1119.0641 | AF39: =SUM(AF27:AF38) -> 1119.0641 | AH39: =SUM(AH27:AH38) -> 1119.0641 | AI39: =SUM(L39:AH39) -> 13083.176
I40: Max | L40: =$C$14*$B$19*$B$21 -> 1316.546 | N40: =$C$14*$B$19*$B$21 -> 1316.546 | P40: =$C$14*$B$19*$B$21 -> 1316.546 | R40: =$C$14*$B$19*$B$21 -> 1316.546 | T40: =$C$14*$B$19*$B$21 -> 1316.546 | V40: =$C$14*$B$19*$B$21 -> 1316.546 | X40: =$C$14*$B$19*$B$21 -> 1316.546 | Z40: =$C$14*$B$19*$B$21 -> 1316.546 | AB40: =$C$14*$B$19*$B$21 -> 1316.546 | AD40: =$C$14*$B$19*$B$21 -> 1316.546 | AF40: =$C$14*$B$19*$B$21 -> 1316.546 | AH40: =$C$14*$B$19*$B$21 -> 1316.546 | AI40: =SUM(L40:AH40) -> 15798.552
I41: Difference | L41: =L40-L39 -> 411.42063 | N41: =N40-N39 -> 308.56547 | P41: =P40-P39 -> 218.05293 | R41: =R40-R39 -> 197.4819 | T41: =T40-T39 -> 197.4819 | V41: =V40-V39 -> 197.4819 | X41: =X40-X39 -> 197.4819 | Z41: =Z40-Z39 -> 197.4819 | AB41: =AB40-AB39 -> 197.4819 | AD41: =AD40-AD39 -> 197.4819 | AF41: =AF40-AF39 -> 197.4819 | AH41: =AH40-AH39 -> 197.4819 | AI41: =SUM(L41:AH41) -> 2715.3761
I42: Total utilization | L42: =L39/L40 -> 0.6875 | N42: =N39/N40 -> 0.765625 | P42: =P39/P40 -> 0.834375 | R42: =R39/R40 -> 0.85 | T42: =T39/T40 -> 0.85 | V42: =V39/V40 -> 0.85 | X42: =X39/X40 -> 0.85 | Z42: =Z39/Z40 -> 0.85 | AB42: =AB39/AB40 -> 0.85 | AD42: =AD39/AD40 -> 0.85 | AF42: =AF39/AF40 -> 0.85 | AH42: =AH39/AH40 -> 0.85 | AI42: =AVERAGE(L42:AH42) -> 0.828125
I43: Month over month growth | L43: 0 | N43: =N42-L42 -> 0.078125 | P43: =P42-N42 -> 0.06875 | R43: =R42-P42 -> 0.015625 | T43: =T42-R42 -> 0 | V43: =V42-T42 -> 0 | X43: =X42-V42 -> 0 | Z43: =Z42-X42 -> 0 | AB43: =AB42-Z42 -> 0 | AD43: =AD42-AB42 -> 0 | AF43: =AF42-AD42 -> 0 | AH43: =AH42-AF42 -> 0 | AI43: =SUM(L43:AH43) -> 0.1625 | AJ43: =AVERAGE(TEAMGROWTH!$L43:$AH43) -> 0.013541667
L44: Jan | N44: Feb | P44: Mar | R44: Apr | T44: May | V44: Jun | X44: Jul | Z44: Aug | AB44: Sep | AD44: Oct | AF44: Nov | AH44: Dec
I45: Total number of 100% Technicians | L45: =Controls!$D$17*L42 -> 5.5 | N45: =Controls!$D$17*N42 -> 6.125 | P45: =Controls!$D$17*P42 -> 6.675 | R45: =Controls!$D$17*R42 -> 6.8 | T45: =Controls!$D$17*T42 -> 6.8 | V45: =Controls!$D$17*V42 -> 6.8 | X45: =Controls!$D$17*X42 -> 6.8 | Z45: =Controls!$D$17*Z42 -> 6.8 | AB45: =Controls!$D$17*AB42 -> 6.8 | AD45: =Controls!$D$17*AD42 -> 6.8 | AF45: =Controls!$D$17*AF42 -> 6.8 | AH45: =Controls!$D$17*AH42 -> 6.8
L48: Jan | M48: Feb | N48: Mar | O48: Apr | P48: May | Q48: Jun | R48: Jul | S48: Aug | T48: Sep | U48: Oct | V48: Nov | W48: Dec
K49: Total number of 100% Technicians | L49: =L45 -> 5.5 | M49: =N45 -> 6.125 | N49: =P45 -> 6.675 | O49: =R45 -> 6.8 | P49: =T45 -> 6.8 | Q49: =V45 -> 6.8 | R49: =X45 -> 6.8 | S49: =Z45 -> 6.8 | T49: =AB45 -> 6.8 | U49: =AD45 -> 6.8 | V49: =AF45 -> 6.8 | W49: =AH45 -> 6.8
A57: Months to hit fully billiable target | B57: Target to High work est | C57: Current | D57: Name | E57: Specific productivity | F57: Position | G57: Billing Rate Growth | H57: Starting Efficientcy | I57: Overall Job Reduction | J57: Column1 | K57: Jan billable rate | L57: Jan BH | M57: Feb billable rate | N57: Feb BH | O57: Mar billable rate | P57: Mar BH | Q57: Apr billable rate | R57: Apr BH | S57: May billable rate | T57: May BH | U57: Jun billable rate | V57: Jun BH | W57: Jul billable rate | X57: Jul BH | Y57: Aug billable rate | Z57: Aug BH | AA57: Sep billable rate | AB57: Sep BH | AC57: Oct billable rate | AD57: Oct BH | AE57: Nov billable rate | AF57: Nov BH | AG57: Dec billable rate | AH57: Dec BH | AI57: Totals
A58: =(B58-C58)*12 -> 0 | C58: ='Work History'!G33 -> 0 | D58: Drew Sandoval | E58: High | F58: AP | G58: =Controls!$G$20 -> 0.125 | H58: 1 | I58: 1 | K58: Avg | L58: =($C$14*$B$19) -> 164.56825 | M58: Avg | N58: =($C$14*$B$19) -> 164.56825 | O58: Avg | P58: =($C$14*$B$19) -> 164.56825 | Q58: Avg | R58: =($C$14*$B$19) -> 164.56825 | S58: Avg | T58: =($C$14*$B$19) -> 164.56825 | U58: Avg | V58: =($C$14*$B$19) -> 164.56825 | W58: Avg | X58: =($C$14*$B$19) -> 164.56825 | Y58: Avg | Z58: =($C$14*$B$19) -> 164.56825 | AA58: Avg | AB58: =($C$14*$B$19) -> 164.56825 | AC58: Avg | AD58: =($C$14*$B$19) -> 164.56825 | AE58: Avg | AF58: =($C$14*$B$19) -> 164.56825 | AG58: Avg | AH58: =($C$14*$B$19) -> 164.56825
J64: Avg | K64: =COUNTIF(K58:K62,"Avg") -> 1 | L64: Avg | M64: =COUNTIF(M58:M62,"Avg") -> 1 | N64: Avg | O64: =COUNTIF(O58:O62,"Avg") -> 1 | P64: Avg | Q64: =COUNTIF(Q58:Q62,"Avg") -> 1 | R64: Avg | S64: =COUNTIF(S58:S62,"Avg") -> 1 | T64: Avg | U64: =COUNTIF(U58:U62,"Avg") -> 1 | V64: Avg | W64: =COUNTIF(W58:W62,"Avg") -> 1 | X64: Avg | Y64: =COUNTIF(Y58:Y62,"Avg") -> 1 | Z64: Avg | AA64: =COUNTIF(AA58:AA62,"Avg") -> 1 | AB64: Avg | AC64: =COUNTIF(AC58:AC62,"Avg") -> 1 | AD64: Avg | AE64: =COUNTIF(AE58:AE62,"Avg") -> 1 | AF64: Avg | AG64: =COUNTIF(AG58:AG62,"Avg") -> 1 | AH64: Avg
J65: Low | K65: =COUNTIF(K58:K62,"low") -> 0 | L65: Low | M65: =COUNTIF(M58:M62,"low") -> 0 | N65: Low | O65: =COUNTIF(O58:O62,"low") -> 0 | P65: Low | Q65: =COUNTIF(Q58:Q62,"low") -> 0 | R65: Low | S65: =COUNTIF(S58:S62,"low") -> 0 | T65: Low | U65: =COUNTIF(U58:U62,"low") -> 0 | V65: Low | W65: =COUNTIF(W58:W62,"low") -> 0 | X65: Low | Y65: =COUNTIF(Y58:Y62,"low") -> 0 | Z65: Low | AA65: =COUNTIF(AA58:AA62,"low") -> 0 | AB65: Low | AC65: =COUNTIF(AC58:AC62,"low") -> 0 | AD65: Low | AE65: =COUNTIF(AE58:AE62,"low") -> 0 | AF65: Low | AG65: =COUNTIF(AG58:AG62,"low") -> 0 | AH65: Low
K66: =K65/(K64+K65) -> 0 | L66: =((SUM(L58:L62)*K66))*($E$4)*-1 -> 0 | M66: =M65/(M64+M65) -> 0 | N66: =((SUM(N58:N62)*M66))*($E$4)*-1 -> 0 | O66: =O65/(O64+O65) -> 0 | P66: =((SUM(P58:P62)*O66))*($E$4)*-1 -> 0 | Q66: =Q65/(Q64+Q65) -> 0 | R66: =((SUM(R58:R62)*Q66))*($E$4)*-1 -> 0 | S66: =S65/(S64+S65) -> 0 | T66: =((SUM(T58:T62)*S66))*($E$4)*-1 -> 0 | U66: =U65/(U64+U65) -> 0 | V66: =((SUM(V58:V62)*U66))*($E$4)*-1 -> 0 | W66: =W65/(W64+W65) -> 0 | X66: =((SUM(X58:X62)*W66))*($E$4)*-1 -> 0 | Y66: =Y65/(Y64+Y65) -> 0 | Z66: =((SUM(Z58:Z62)*Y66))*($E$4)*-1 -> 0 | AA66: =AA65/(AA64+AA65) -> 0 | AB66: =((SUM(AB58:AB62)*AA66))*($E$4)*-1 -> 0 | AC66: =AC65/(AC64+AC65) -> 0 | AD66: =((SUM(AD58:AD62)*AC66))*($E$4)*-1 -> 0 | AE66: =AE65/(AE64+AE65) -> 0 | AF66: =((SUM(AF58:AF62)*AE66))*($E$4)*-1 -> 0 | AG66: =AG65/(AG64+AG65) -> 0 | AH66: =((SUM(AH58:AH62)*AG66))*($E$4)*-1 -> 0
I67: Total | L67: =SUM(L58:L66) -> 164.56825 | N67: =SUM(N58:N66) -> 164.56825 | P67: =SUM(P58:P66) -> 164.56825 | R67: =SUM(R58:R66) -> 164.56825 | T67: =SUM(T58:T66) -> 164.56825 | V67: =SUM(V58:V66) -> 164.56825 | X67: =SUM(X58:X66) -> 164.56825 | Z67: =SUM(Z58:Z66) -> 164.56825 | AB67: =SUM(AB58:AB66) -> 164.56825 | AD67: =SUM(AD58:AD66) -> 164.56825 | AF67: =SUM(AF58:AF66) -> 164.56825 | AH67: =SUM(AH58:AH66) -> 164.56825 | AI67: =SUM(L67:AH67) -> 1974.819
I68: Max | L68: =$C$14*$B$19*$B$22 -> 164.56825 | N68: =$C$14*$B$19*$B$22 -> 164.56825 | P68: =$C$14*$B$19*$B$22 -> 164.56825 | R68: =$C$14*$B$19*$B$22 -> 164.56825 | T68: =$C$14*$B$19*$B$22 -> 164.56825 | V68: =$C$14*$B$19*$B$22 -> 164.56825 | X68: =$C$14*$B$19*$B$22 -> 164.56825 | Z68: =$C$14*$B$19*$B$22 -> 164.56825 | AB68: =$C$14*$B$19*$B$22 -> 164.56825 | AD68: =$C$14*$B$19*$B$22 -> 164.56825 | AF68: =$C$14*$B$19*$B$22 -> 164.56825 | AH68: =$C$14*$B$19*$B$22 -> 164.56825 | AI68: =SUM(L68:AH68) -> 1974.819
I69: Difference | L69: =L68-L67 -> 0 | N69: =N68-N67 -> 0 | P69: =P68-P67 -> 0 | R69: =R68-R67 -> 0 | T69: =T68-T67 -> 0 | V69: =V68-V67 -> 0 | X69: =X68-X67 -> 0 | Z69: =Z68-Z67 -> 0 | AB69: =AB68-AB67 -> 0 | AD69: =AD68-AD67 -> 0 | AF69: =AF68-AF67 -> 0 | AH69: =AH68-AH67 -> 0 | AI69: =SUM(L69:AH69) -> 0
I70: Total utilization | L70: =L67/L68 -> 1 | N70: =N67/N68 -> 1 | P70: =P67/P68 -> 1 | R70: =R67/R68 -> 1 | T70: =T67/T68 -> 1 | V70: =V67/V68 -> 1 | X70: =X67/X68 -> 1 | Z70: =Z67/Z68 -> 1 | AB70: =AB67/AB68 -> 1 | AD70: =AD67/AD68 -> 1 | AF70: =AF67/AF68 -> 1 | AH70: =AH67/AH68 -> 1 | AI70: =AVERAGE(L70:AH70) -> 1
I71: Month over month growth | L71: 0 | N71: =N70-L70 -> 0 | P71: =P70-N70 -> 0 | R71: =R70-P70 -> 0 | T71: =T70-R70 -> 0 | V71: =V70-T70 -> 0 | X71: =X70-V70 -> 0 | Z71: =Z70-X70 -> 0 | AB71: =AB70-Z70 -> 0 | AD71: =AD70-AB70 -> 0 | AF71: =AF70-AD70 -> 0 | AH71: =AH70-AF70 -> 0 | AI71: =SUM(L71:AH71) -> 0 | AJ71: =AVERAGE(TEAMGROWTH!$L71:$AH71) -> 0
L72: Jan | N72: Feb | P72: Mar | R72: Apr | T72: May | V72: Jun | X72: Jul | Z72: Aug | AB72: Sep | AD72: Oct | AF72: Nov | AH72: Dec
I73: Total number of 100% Technicians | L73: =Controls!$D$18*L70 -> 1 | N73: =Controls!$D$18*N70 -> 1 | P73: =Controls!$D$18*P70 -> 1 | R73: =Controls!$D$18*R70 -> 1 | T73: =Controls!$D$18*T70 -> 1 | V73: =Controls!$D$18*V70 -> 1 | X73: =Controls!$D$18*X70 -> 1 | Z73: =Controls!$D$18*Z70 -> 1 | AB73: =Controls!$D$18*AB70 -> 1 | AD73: =Controls!$D$18*AD70 -> 1 | AF73: =Controls!$D$18*AF70 -> 1 | AH73: =Controls!$D$18*AH70 -> 1
L76: Jan | M76: Feb | N76: Mar | O76: Apr | P76: May | Q76: Jun | R76: Jul | S76: Aug | T76: Sep | U76: Oct | V76: Nov | W76: Dec
K77: Total number of 100% Technicians | L77: =L73 -> 1 | M77: =N73 -> 1 | N77: =P73 -> 1 | O77: =R73 -> 1 | P77: =T73 -> 1 | Q77: =V73 -> 1 | R77: =X73 -> 1 | S77: =Z73 -> 1 | T77: =AB73 -> 1 | U77: =AD73 -> 1 | V77: =AF73 -> 1 | W77: =AH73 -> 1
